[{
  "_id": {
    "$oid": "64ef55ed9134d0297553a3e6"
  },
  "name": "fshst "
},
{
  "_id": {
    "$oid": "64ef55ed9134d0297553a3e7"
  },
  "name": "essect "
},
{
  "_id": {
    "$oid": "64ef55ed9134d0297553a3e8"
  },
  "name": "ens "
},
{
  "_id": {
    "$oid": "64ef55ed9134d0297553a3e9"
  },
  "name": "ensit"
},
{
  "_id": {
    "$oid": "64ef55ed9134d0297553a3ea"
  },
  "name": "ipeit"
},
{
  "_id": {
    "$oid": "64ef55ed9134d0297553a3eb"
  },
  "name": "issat"
},
{
  "_id": {
    "$oid": "64ef55ed9134d0297553a3ec"
  },
  "name": "isi"
},
{
  "_id": {
    "$oid": "64ef55ed9134d0297553a3ed"
  },
  "name": "iset"
},
{
  "_id": {
    "$oid": "64ef55ed9134d0297553a3ee"
  },
  "name": "insat"
},
{
  "_id": {
    "$oid": "64ef55ed9134d0297553a3ef"
  },
  "name": "ipelsht"
},
{
  "_id": {
    "$oid": "64ef55ed9134d0297553a3f0"
  },
  "name": "isg"
},
{
  "_id": {
    "$oid": "64ef55ed9134d0297553a3f1"
  },
  "name": "isbat"
},
{
  "_id": {
    "$oid": "64ef55ed9134d0297553a3f2"
  },
  "name": "ismt"
},
{
  "_id": {
    "$oid": "64ef55ed9134d0297553a3f3"
  },
  "name": "isad"
},
{
  "_id": {
    "$oid": "64ef55ed9134d0297553a3f4"
  },
  "name": "ismpt"
},
{
  "_id": {
    "$oid": "64ef55ed9134d0297553a3f5"
  },
  "name": "iseaht"
},
{
  "_id": {
    "$oid": "64ef55ed9134d0297553a3f6"
  },
  "name": "isajc"
},
{
  "_id": {
    "$oid": "64ef55ed9134d0297553a3f7"
  },
  "name": "iseahz"
},
{
  "_id": {
    "$oid": "64ef55ed9134d0297553a3f8"
  },
  "name": "inp"
},
{
  "_id": {
    "$oid": "64ef55ed9134d0297553a3f9"
  },
  "name": "fsjps"
},
{
  "_id": {
    "$oid": "64ef55ed9134d0297553a3fa"
  },
  "name": "fsb"
},
{
  "_id": {
    "$oid": "64ef55ed9134d0297553a3fb"
  },
  "name": "fsegn"
},
{
  "_id": {
    "$oid": "64ef55ed9134d0297553a3fc"
  },
  "name": "enau"
},
{
  "_id": {
    "$oid": "64ef55ed9134d0297553a3fd"
  },
  "name": "ept"
},
{
  "_id": {
    "$oid": "64ef55ed9134d0297553a3fe"
  },
  "name": "enicarthage"
},
{
  "_id": {
    "$oid": "64ef55ed9134d0297553a3ff"
  },
  "name": "enicar"
},
{
  "_id": {
    "$oid": "64ef55ed9134d0297553a400"
  },
  "name": "essai"
},
{
  "_id": {
    "$oid": "64ef55ed9134d0297553a401"
  },
  "name": "esac"
},
{
  "_id": {
    "$oid": "64ef55ed9134d0297553a402"
  },
  "name": "ipeib"
},
{
  "_id": {
    "$oid": "64ef55ed9134d0297553a403"
  },
  "name": "ihec"
},
{
  "_id": {
    "$oid": "64ef55ed9134d0297553a404"
  },
  "name": "insat"
},
{
  "_id": {
    "$oid": "64ef55ed9134d0297553a405"
  },
  "name": "issatm"
},
{
  "_id": {
    "$oid": "64ef55ed9134d0297553a406"
  },
  "name": "ipein"
},
{
  "_id": {
    "$oid": "64ef55ed9134d0297553a407"
  },
  "name": "isban"
},
{
  "_id": {
    "$oid": "64ef55ed9134d0297553a408"
  },
  "name": "isteub"
},
{
  "_id": {
    "$oid": "64ef55ed9134d0297553a409"
  },
  "name": "islt"
},
{
  "_id": {
    "$oid": "64ef55ed9134d0297553a40a"
  },
  "name": "isln"
},
{
  "_id": {
    "$oid": "64ef55ed9134d0297553a40b"
  },
  "name": "isste"
},
{
  "_id": {
    "$oid": "64ef55ed9134d0297553a40c"
  },
  "name": "isccb"
},
{
  "_id": {
    "$oid": "64ef55ed9134d0297553a40d"
  },
  "name": "isgbz"
},
{
  "_id": {
    "$oid": "64ef55ed9134d0297553a40e"
  },
  "name": "supcom"
},
{
  "_id": {
    "$oid": "64ef55ed9134d0297553a40f"
  },
  "name": "isepbgsoukra"
},
{
  "_id": {
    "$oid": "64ef55ed9134d0297553a410"
  },
  "name": "isepb"
},
{
  "_id": {
    "$oid": "64ef55ed9134d0297553a411"
  },
  "name": "esamog"
},
{
  "_id": {
    "$oid": "64ef55ed9134d0297553a412"
  },
  "name": "esamat"
},
{
  "_id": {
    "$oid": "64ef55ed9134d0297553a413"
  },
  "name": "esiat"
},
{
  "_id": {
    "$oid": "64ef55ed9134d0297553a414"
  },
  "name": "ispab"
},
{
  "_id": {
    "$oid": "64ef55ed9134d0297553a415"
  },
  "name": "intes"
},
{
  "_id": {
    "$oid": "64ef55ed9134d0297553a416"
  },
  "name": "iscenf"
},
{
  "_id": {
    "$oid": "64ef55ed9134d0297553a417"
  },
  "name": "inat"
},
{
  "_id": {
    "$oid": "64ef55ed9134d0297553a418"
  },
  "name": "ihet"
},
{
  "_id": {
    "$oid": "64ef55ed9134d0297553a419"
  },
  "name": "inrgref"
},
{
  "_id": {
    "$oid": "64ef55ed9134d0297553a41a"
  },
  "name": "inrat"
},
{
  "_id": {
    "$oid": "64ef55ed9134d0297553a41b"
  },
  "name": "enstab"
},
{
  "_id": {
    "$oid": "64ef55ed9134d0297553a41c"
  },
  "name": "enib"
},
{
  "_id": {
    "$oid": "64ef55ed9134d0297553a41d"
  },
  "name": "istic"
},
{
  "_id": {
    "$oid": "64ef55ed9134d0297553a41e"
  },
  "name": "fsg"
},
{
  "_id": {
    "$oid": "64ef55ed9134d0297553a41f"
  },
  "name": "enig"
},
{
  "_id": {
    "$oid": "64ef55ed9134d0297553a420"
  },
  "name": "isggb"
},
{
  "_id": {
    "$oid": "64ef55ed9134d0297553a421"
  },
  "name": "islgb"
},
{
  "_id": {
    "$oid": "64ef55ed9134d0297553a422"
  },
  "name": "isamgb"
},
{
  "_id": {
    "$oid": "64ef55ed9134d0297553a423"
  },
  "name": "isbam"
},
{
  "_id": {
    "$oid": "64ef55ed9134d0297553a424"
  },
  "name": "isejg"
},
{
  "_id": {
    "$oid": "64ef55ed9134d0297553a425"
  },
  "name": "isimg"
},
{
  "_id": {
    "$oid": "64ef55ed9134d0297553a426"
  },
  "name": "issatgb"
},
{
  "_id": {
    "$oid": "64ef55ed9134d0297553a427"
  },
  "name": "issig"
},
{
  "_id": {
    "$oid": "64ef55ed9134d0297553a428"
  },
  "name": "iseahmd"
},
{
  "_id": {
    "$oid": "64ef55ed9134d0297553a429"
  },
  "name": "isim"
},
{
  "_id": {
    "$oid": "64ef55ed9134d0297553a42a"
  },
  "name": "isamt"
},
{
  "_id": {
    "$oid": "64ef55ed9134d0297553a42b"
  },
  "name": "issig"
},
{
  "_id": {
    "$oid": "64ef55ed9134d0297553a42c"
  },
  "name": "fsm"
},
{
  "_id": {
    "$oid": "64ef55ed9134d0297553a42d"
  },
  "name": "fmm"
},
{
  "_id": {
    "$oid": "64ef55ed9134d0297553a42e"
  },
  "name": "isimm"
},
{
  "_id": {
    "$oid": "64ef55ed9134d0297553a42f"
  },
  "name": "fmdm"
},
{
  "_id": {
    "$oid": "64ef55ed9134d0297553a430"
  },
  "name": "fphm"
},
{
  "_id": {
    "$oid": "64ef55ed9134d0297553a431"
  },
  "name": "enim"
},
{
  "_id": {
    "$oid": "64ef55ed9134d0297553a432"
  },
  "name": "isbm"
},
{
  "_id": {
    "$oid": "64ef55ed9134d0297553a433"
  },
  "name": "ipeim"
},
{
  "_id": {
    "$oid": "64ef55ed9134d0297553a434"
  },
  "name": "esstsm"
},
{
  "_id": {
    "$oid": "64ef55ed9134d0297553a435"
  },
  "name": "iseahm"
},
{
  "_id": {
    "$oid": "64ef55ed9134d0297553a436"
  },
  "name": "ismmm"
},
{
  "_id": {
    "$oid": "64ef55ed9134d0297553a437"
  },
  "name": "isima"
},
{
  "_id": {
    "$oid": "64ef55ed9134d0297553a438"
  },
  "name": "isammh"
},
{
  "_id": {
    "$oid": "64ef55ed9134d0297553a439"
  },
  "name": "issatmh"
},
{
  "_id": {
    "$oid": "64ef55ed9134d0297553a43a"
  },
  "name": "islaatm"
},
{
  "_id": {
    "$oid": "64ef55ed9134d0297553a43b"
  },
  "name": "isth"
},
{
  "_id": {
    "$oid": "64ef55ed9134d0297553a43c"
  },
  "name": "isci"
},
{
  "_id": {
    "$oid": "64ef55ed9134d0297553a43d"
  },
  "name": "ceik"
},
{
  "_id": {
    "$oid": "64ef55ed9134d0297553a43e"
  },
  "name": "isamk"
},
{
  "_id": {
    "$oid": "64ef55ed9134d0297553a43f"
  },
  "name": "isigk"
},
{
  "_id": {
    "$oid": "64ef55ed9134d0297553a440"
  },
  "name": "isejpk"
},
{
  "_id": {
    "$oid": "64ef55ed9134d0297553a441"
  },
  "name": "issatkr"
},
{
  "_id": {
    "$oid": "64ef55ed9134d0297553a442"
  },
  "name": "ismakas"
},
{
  "_id": {
    "$oid": "64ef55ed9134d0297553a443"
  },
  "name": "isamkas"
},
{
  "_id": {
    "$oid": "64ef55ed9134d0297553a444"
  },
  "name": "ismaik"
},
{
  "_id": {
    "$oid": "64ef55ed9134d0297553a445"
  },
  "name": "iseahs"
},
{
  "_id": {
    "$oid": "64ef55ed9134d0297553a446"
  },
  "name": "isamsb"
},
{
  "_id": {
    "$oid": "64ef55ed9134d0297553a447"
  },
  "name": "ipeik"
},
{
  "_id": {
    "$oid": "64ef55ed9134d0297553a448"
  },
  "name": "fstbz"
},
{
  "_id": {
    "$oid": "64ef55ed9134d0297553a449"
  },
  "name": "issatkas"
},
{
  "_id": {
    "$oid": "64ef55ed9134d0297553a44a"
  },
  "name": "isetsf"
},
{
  "_id": {
    "$oid": "64ef55ed9134d0297553a44b"
  },
  "name": "isetke"
},
{
  "_id": {
    "$oid": "64ef55ed9134d0297553a44c"
  },
  "name": "isetgb"
},
{
  "_id": {
    "$oid": "64ef55ed9134d0297553a44d"
  },
  "name": "isetjb"
},
{
  "_id": {
    "$oid": "64ef55ed9134d0297553a44e"
  },
  "name": "isetkf"
},
{
  "_id": {
    "$oid": "64ef55ed9134d0297553a44f"
  },
  "name": "isetzg"
},
{
  "_id": {
    "$oid": "64ef55ed9134d0297553a450"
  },
  "name": "isetso"
},
{
  "_id": {
    "$oid": "64ef55ed9134d0297553a451"
  },
  "name": "isetma"
},
{
  "_id": {
    "$oid": "64ef55ed9134d0297553a452"
  },
  "name": "isetsl"
},
{
  "_id": {
    "$oid": "64ef55ed9134d0297553a453"
  },
  "name": "isetr"
},
{
  "_id": {
    "$oid": "64ef55ed9134d0297553a454"
  },
  "name": "isetn"
},
{
  "_id": {
    "$oid": "64ef55ed9134d0297553a455"
  },
  "name": "isetsbz"
},
{
  "_id": {
    "$oid": "64ef55ed9134d0297553a456"
  },
  "name": "isetcom"
},
{
  "_id": {
    "$oid": "64ef55ed9134d0297553a457"
  },
  "name": "isetkr"
},
{
  "_id": {
    "$oid": "64ef55ed9134d0297553a458"
  },
  "name": "isetgf"
},
{
  "_id": {
    "$oid": "64ef55ed9134d0297553a459"
  },
  "name": "isetb"
},
{
  "_id": {
    "$oid": "64ef55ed9134d0297553a45a"
  },
  "name": "isetch"
},
{
  "_id": {
    "$oid": "64ef55ed9134d0297553a45b"
  },
  "name": "isetj"
},
{
  "_id": {
    "$oid": "64ef55ed9134d0297553a45c"
  },
  "name": "isetks"
},
{
  "_id": {
    "$oid": "64ef55ed9134d0297553a45d"
  },
  "name": "isetkh"
},
{
  "_id": {
    "$oid": "64ef55ed9134d0297553a45e"
  },
  "name": "isetta"
},
{
  "_id": {
    "$oid": "64ef55ed9134d0297553a45f"
  },
  "name": "isett"
},
{
  "_id": {
    "$oid": "64ef55ed9134d0297553a460"
  },
  "name": "isetb"
},
{
  "_id": {
    "$oid": "64ef55ed9134d0297553a461"
  },
  "name": "isetmd"
},
{
  "_id": {
    "$oid": "64ef55ed9134d0297553a462"
  },
  "name": "fdspt"
},
{
  "_id": {
    "$oid": "64ef55ed9134d0297553a463"
  },
  "name": "fsegt"
},
{
  "_id": {
    "$oid": "64ef55ed9134d0297553a464"
  },
  "name": "fst"
},
{
  "_id": {
    "$oid": "64ef55ed9134d0297553a465"
  },
  "name": "fmt"
},
{
  "_id": {
    "$oid": "64ef55ed9134d0297553a466"
  },
  "name": "enit"
},
{
  "_id": {
    "$oid": "64ef55ed9134d0297553a467"
  },
  "name": "iblv"
},
{
  "_id": {
    "$oid": "64ef55ed9134d0297553a468"
  },
  "name": "ipeiem"
},
{
  "_id": {
    "$oid": "64ef55ed9134d0297553a469"
  },
  "name": "issbat"
},
{
  "_id": {
    "$oid": "64ef55ed9134d0297553a46a"
  },
  "name": "isi"
},
{
  "_id": {
    "$oid": "64ef55ed9134d0297553a46b"
  },
  "name": "issht"
},
{
  "_id": {
    "$oid": "64ef55ed9134d0297553a46c"
  },
  "name": "istmt"
},
{
  "_id": {
    "$oid": "64ef55ed9134d0297553a46d"
  },
  "name": "esstst"
},
{
  "_id": {
    "$oid": "64ef55ed9134d0297553a46e"
  },
  "name": "issit"
},
{
  "_id": {
    "$oid": "64ef55ed9134d0297553a46f"
  },
  "name": "irvt"
},
{
  "_id": {
    "$oid": "64ef55ed9134d0297553a470"
  },
  "name": "fsjegj"
},
{
  "_id": {
    "$oid": "64ef55ed9134d0297553a471"
  },
  "name": "iseahkf"
},
{
  "_id": {
    "$oid": "64ef55ed9134d0297553a472"
  },
  "name": "islaib"
},
{
  "_id": {
    "$oid": "64ef55ed9134d0297553a473"
  },
  "name": "isshj"
},
{
  "_id": {
    "$oid": "64ef55ed9134d0297553a474"
  },
  "name": "isamsl"
},
{
  "_id": {
    "$oid": "64ef55ed9134d0297553a475"
  },
  "name": "istmk"
},
{
  "_id": {
    "$oid": "64ef55ed9134d0297553a476"
  },
  "name": "esakef"
},
{
  "_id": {
    "$oid": "64ef55ed9134d0297553a477"
  },
  "name": "isptabarka"
},
{
  "_id": {
    "$oid": "64ef55ed9134d0297553a478"
  },
  "name": "esier"
},
{
  "_id": {
    "$oid": "64ef55ed9134d0297553a479"
  },
  "name": "isikef"
},
{
  "_id": {
    "$oid": "64ef55ed9134d0297553a47a"
  },
  "name": "isbb"
},
{
  "_id": {
    "$oid": "64ef55ed9134d0297553a47b"
  },
  "name": "issikf"
},
{
  "_id": {
    "$oid": "64ef55ed9134d0297553a47c"
  },
  "name": "fdsps"
},
{
  "_id": {
    "$oid": "64ef55ed9134d0297553a47d"
  },
  "name": "fls"
},
{
  "_id": {
    "$oid": "64ef55ed9134d0297553a47e"
  },
  "name": "isffs"
},
{
  "_id": {
    "$oid": "64ef55ed9134d0297553a47f"
  },
  "name": "infcom"
},
{
  "_id": {
    "$oid": "64ef55ed9134d0297553a480"
  },
  "name": "istls"
},
{
  "_id": {
    "$oid": "64ef55ed9134d0297553a481"
  },
  "name": "isbas"
},
{
  "_id": {
    "$oid": "64ef55ed9134d0297553a482"
  },
  "name": "esstssousse"
},
{
  "_id": {
    "$oid": "64ef55ed9134d0297553a483"
  },
  "name": "essts"
},
{
  "_id": {
    "$oid": "64ef55ed9134d0297553a484"
  },
  "name": "isgs"
},
{
  "_id": {
    "$oid": "64ef55ed9134d0297553a485"
  },
  "name": "ihecso"
},
{
  "_id": {
    "$oid": "64ef55ed9134d0297553a486"
  },
  "name": "ismso"
},
{
  "_id": {
    "$oid": "64ef55ed9134d0297553a487"
  },
  "name": "issatso"
},
{
  "_id": {
    "$oid": "64ef55ed9134d0297553a488"
  },
  "name": "eniso"
},
{
  "_id": {
    "$oid": "64ef55ed9134d0297553a489"
  },
  "name": "essths"
},
{
  "_id": {
    "$oid": "64ef55ed9134d0297553a48a"
  },
  "name": "fsegso"
},
{
  "_id": {
    "$oid": "64ef55ed9134d0297553a48b"
  },
  "name": "fsegs"
},
{
  "_id": {
    "$oid": "64ef55ed9134d0297553a48c"
  },
  "name": "fmsf"
},
{
  "_id": {
    "$oid": "64ef55ed9134d0297553a48d"
  },
  "name": "fdsf"
},
{
  "_id": {
    "$oid": "64ef55ed9134d0297553a48e"
  },
  "name": "isams"
},
{
  "_id": {
    "$oid": "64ef55ed9134d0297553a48f"
  },
  "name": "enetcom"
},
{
  "_id": {
    "$oid": "64ef55ed9134d0297553a490"
  },
  "name": "isgis"
},
{
  "_id": {
    "$oid": "64ef55ed9134d0297553a491"
  },
  "name": "ihecsf"
},
{
  "_id": {
    "$oid": "64ef55ed9134d0297553a492"
  },
  "name": "fss"
},
{
  "_id": {
    "$oid": "64ef55ed9134d0297553a493"
  },
  "name": "enis"
},
{
  "_id": {
    "$oid": "64ef55ed9134d0297553a494"
  },
  "name": "escs"
},
{
  "_id": {
    "$oid": "64ef55ed9134d0297553a495"
  },
  "name": "isaas"
},
{
  "_id": {
    "$oid": "64ef55ed9134d0297553a496"
  },
  "name": "isimsf"
},
{
  "_id": {
    "$oid": "64ef55ed9134d0297553a497"
  },
  "name": "ismsf"
},
{
  "_id": {
    "$oid": "64ef55ed9134d0297553a498"
  },
  "name": "ipeis"
},
{
  "_id": {
    "$oid": "64ef55ed9134d0297553a499"
  },
  "name": "isbs"
},
{
  "_id": {
    "$oid": "64ef55ed9134d0297553a49a"
  },
  "name": "flshs"
},
{
  "_id": {
    "$oid": "64ef55ed9134d0297553a49b"
  },
  "name": "iosfax"
},
{
  "_id": {
    "$oid": "64ef55ed9134d0297553a49c"
  },
  "name": "issisfax"
},
{
  "_id": {
    "$oid": "64ef55ed9134d0297553a49d"
  },
  "name": "flm"
},
{
  "_id": {
    "$oid": "64ef55ed9134d0297553a49e"
  },
  "name": "essted"
},
{
  "_id": {
    "$oid": "64ef55ed9134d0297553a49f"
  },
  "name": "esct"
},
{
  "_id": {
    "$oid": "64ef55ed9134d0297553a4a0"
  },
  "name": "esen"
},
{
  "_id": {
    "$oid": "64ef55ed9134d0297553a4a1"
  },
  "name": "ensi "
},
{
  "_id": {
    "$oid": "64ef55ed9134d0297553a4a2"
  },
  "name": "isamm"
},
{
  "_id": {
    "$oid": "64ef55ed9134d0297553a4a3"
  },
  "name": "iscae"
},
{
  "_id": {
    "$oid": "64ef55ed9134d0297553a4a4"
  },
  "name": "isbst"
},
{
  "_id": {
    "$oid": "64ef55ed9134d0297553a4a5"
  },
  "name": "isd"
},
{
  "_id": {
    "$oid": "64ef55ed9134d0297553a4a6"
  },
  "name": "ipsi"
},
{
  "_id": {
    "$oid": "64ef55ed9134d0297553a4a7"
  },
  "name": "enmv"
},
{
  "_id": {
    "$oid": "64ef55ed9134d0297553a4a8"
  },
  "name": "issep-ks"
},
{
  "_id": {
    "$oid": "64ef55ed9134d0297553a4a9"
  },
  "name": "issep"
},
{
  "_id": {
    "$oid": "64ef55ed9134d0297553a4aa"
  },
  "name": "ises"
},
{
  "_id": {
    "$oid": "64ef55ed9134d0297553a4ab"
  },
  "name": "ishmn"
},
{
  "_id": {
    "$oid": "64ef55ed9134d0297553a4ac"
  },
  "name": "fsgf"
},
{
  "_id": {
    "$oid": "64ef55ed9134d0297553a4ad"
  },
  "name": "iseahgf"
},
{
  "_id": {
    "$oid": "64ef55ed9134d0297553a4ae"
  },
  "name": "isaeg"
},
{
  "_id": {
    "$oid": "64ef55ed9134d0297553a4af"
  },
  "name": "issatgf"
},
{
  "_id": {
    "$oid": "64ef55ed9134d0297553a4b0"
  },
  "name": "isamgf"
},
{
  "_id": {
    "$oid": "64ef55ed9134d0297553a4b1"
  },
  "name": "issteg"
},
{
  "_id": {
    "$oid": "64ef55ed9134d0297553a4b2"
  },
  "name": "iseahtz"
},
{
  "_id": {
    "$oid": "64ef55ed9134d0297553a4b3"
  },
  "name": "ipeig"
},
{
  "_id": {
    "$oid": "64ef55ed9134d0297553a4b4"
  },
  "name": "issepgf"
},
{
  "_id": {
    "$oid": "64ef55ed9134d0297553a4b5"
  },
  "name": "eniga"
},
{
  "_id": {
    "$oid": "64ef55ed9134d0297553a4b6"
  },
  "name": "isefc"
},
{
  "_id": {
    "$oid": "64ef55ed9134d0297553a4b7"
  },
  "name": "esprit "
},
{
  "_id": {
    "$oid": "64ef55ed9134d0297553a4b8"
  },
  "name": "epi "
},
{
  "_id": {
    "$oid": "64ef55ed9134d0297553a4b9"
  },
  "name": "ECSPSPT"
},
{
  "_id": {
    "$oid": "64ef55ed9134d0297553a4ba"
  },
  "name": "ECSPLAS"
},
{
  "_id": {
    "$oid": "64ef55ed9134d0297553a4bb"
  },
  "name": "ECSPDG"
},
{
  "_id": {
    "$oid": "64ef55ed9134d0297553a4bc"
  },
  "name": "EISPT"
},
{
  "_id": {
    "$oid": "64ef55ed9134d0297553a4bd"
  },
  "name": "EMSPA"
},
{
  "_id": {
    "$oid": "64ef55ed9134d0297553a4be"
  },
  "name": "EMSPP"
},
{
  "_id": {
    "$oid": "64ef55ed9134d0297553a4bf"
  },
  "name": "ESIPT"
},
{
  "_id": {
    "$oid": "64ef55ed9134d0297553a4c0"
  },
  "name": "ESPCPT"
},
{
  "_id": {
    "$oid": "64ef55ed9134d0297553a4c1"
  },
  "name": "ESPIT"
},
{
  "_id": {
    "$oid": "64ef55ed9134d0297553a4c2"
  },
  "name": "ESCSCI"
},
{
  "_id": {
    "$oid": "64ef55ed9134d0297553a4c3"
  },
  "name": "ESCCM"
},
{
  "_id": {
    "$oid": "64ef55ed9134d0297553a4c4"
  },
  "name": "ESPDM"
},
{
  "_id": {
    "$oid": "64ef55ed9134d0297553a4c5"
  },
  "name": "ESPAT"
},
{
  "_id": {
    "$oid": "64ef55ed9134d0297553a4c6"
  },
  "name": "ESPAD"
},
{
  "_id": {
    "$oid": "64ef55ed9134d0297553a4c7"
  },
  "name": "ESPTM"
},
{
  "_id": {
    "$oid": "64ef55ed9134d0297553a4c8"
  },
  "name": "ESPTIAE"
},
{
  "_id": {
    "$oid": "64ef55ed9134d0297553a4c9"
  },
  "name": "ESPTI"
},
{
  "_id": {
    "$oid": "64ef55ed9134d0297553a4ca"
  },
  "name": "ESPSAM"
},
{
  "_id": {
    "$oid": "64ef55ed9134d0297553a4cb"
  },
  "name": "ESPAAD"
},
{
  "_id": {
    "$oid": "64ef55ed9134d0297553a4cc"
  },
  "name": "ESPIAA"
},
{
  "_id": {
    "$oid": "64ef55ed9134d0297553a4cd"
  },
  "name": "ESPIC"
},
{
  "_id": {
    "$oid": "64ef55ed9134d0297553a4ce"
  },
  "name": "ESPIET"
},
{
  "_id": {
    "$oid": "64ef55ed9134d0297553a4cf"
  },
  "name": "ESPPIKH"
},
{
  "_id": {
    "$oid": "64ef55ed9134d0297553a4d0"
  },
  "name": "ESPLBS"
},
{
  "_id": {
    "$oid": "64ef55ed9134d0297553a4d1"
  },
  "name": "ESGIT"
},
{
  "_id": {
    "$oid": "64ef55ed9134d0297553a4d2"
  },
  "name": "ESPMST"
},
{
  "_id": {
    "$oid": "64ef55ed9134d0297553a4d3"
  },
  "name": "FMPSIEG"
},
{
  "_id": {
    "$oid": "64ef55ed9134d0297553a4d4"
  },
  "name": "FPDEG"
},
{
  "_id": {
    "$oid": "64ef55ed9134d0297553a4d5"
  },
  "name": "FPM"
},
{
  "_id": {
    "$oid": "64ef55ed9134d0297553a4d6"
  },
  "name": "FSGTM"
},
{
  "_id": {
    "$oid": "64ef55ed9134d0297553a4d7"
  },
  "name": "FPSS"
},
{
  "_id": {
    "$oid": "64ef55ed9134d0297553a4d8"
  },
  "name": "FPSJSE"
},
{
  "_id": {
    "$oid": "64ef55ed9134d0297553a4d9"
  },
  "name": "FPIDSEG"
},
{
  "_id": {
    "$oid": "64ef55ed9134d0297553a4da"
  },
  "name": "IISPENA"
},
{
  "_id": {
    "$oid": "64ef55ed9134d0297553a4db"
  },
  "name": "IPHE"
},
{
  "_id": {
    "$oid": "64ef55ed9134d0297553a4dc"
  },
  "name": "ISPSM"
},
{
  "_id": {
    "$oid": "64ef55ed9134d0297553a4dd"
  },
  "name": "ISPAE"
},
{
  "_id": {
    "$oid": "64ef55ed9134d0297553a4de"
  },
  "name": "ISPMT"
},
{
  "_id": {
    "$oid": "64ef55ed9134d0297553a4df"
  },
  "name": "ISPP"
},
{
  "_id": {
    "$oid": "64ef55ed9134d0297553a4e0"
  },
  "name": "ISPTD"
},
{
  "_id": {
    "$oid": "64ef55ed9134d0297553a4e1"
  },
  "name": "Faculté des Sciences Humaines et Sociales de Tunis"
},
{
  "_id": {
    "$oid": "64ef55ed9134d0297553a4e2"
  },
  "name": "Ecole Supérieure des Sciences Economiques et Commerciales de Tunis"
},
{
  "_id": {
    "$oid": "64ef55ed9134d0297553a4e3"
  },
  "name": "Ecole Normale Supérieure"
},
{
  "_id": {
    "$oid": "64ef55ed9134d0297553a4e4"
  },
  "name": "Ecole Supérieure des Sciences et Techniques de Tunis"
},
{
  "_id": {
    "$oid": "64ef55ed9134d0297553a4e5"
  },
  "name": "Institut Préparatoire aux Etudes d'Ingénieurs de Tunis"
},
{
  "_id": {
    "$oid": "64ef55ed9134d0297553a4e6"
  },
  "name": "Institut Préparatoire aux Etudes Littéraires et de Sciences Humaines de Tunis"
},
{
  "_id": {
    "$oid": "64ef55ed9134d0297553a4e7"
  },
  "name": "Institut Supérieur de Gestion de Tunis"
},
{
  "_id": {
    "$oid": "64ef55ed9134d0297553a4e8"
  },
  "name": "Institut Supérieur de l'Education et de la Formation Continue"
},
{
  "_id": {
    "$oid": "64ef55ed9134d0297553a4e9"
  },
  "name": "Institut Supérieur des Beaux Arts de Tunis"
},
{
  "_id": {
    "$oid": "64ef55ed9134d0297553a4ea"
  },
  "name": "Institut Supérieur de Musique"
},
{
  "_id": {
    "$oid": "64ef55ed9134d0297553a4eb"
  },
  "name": "Institut Supérieur d'Art Dramatique"
},
{
  "_id": {
    "$oid": "64ef55ed9134d0297553a4ec"
  },
  "name": "Institut Supérieur des Sciences Culturelles et Métiers du Patrimoine de Tunis"
},
{
  "_id": {
    "$oid": "64ef55ed9134d0297553a4ed"
  },
  "name": "Institut Supérieur des Etudes Appliquées en Humanités de Tunis"
},
{
  "_id": {
    "$oid": "64ef55ed9134d0297553a4ee"
  },
  "name": "Institut Supérieur de l'Animation pour la Jeunesse et la Culture"
},
{
  "_id": {
    "$oid": "64ef55ed9134d0297553a4ef"
  },
  "name": "Institut Supérieur des Études Appliquées en Humanités de Zaghouan"
},
{
  "_id": {
    "$oid": "64ef55ed9134d0297553a4f0"
  },
  "name": "Institut National du Patrimoine"
},
{
  "_id": {
    "$oid": "64ef55ed9134d0297553a4f1"
  },
  "name": "Tunis Business School"
},
{
  "_id": {
    "$oid": "64ef55ed9134d0297553a4f2"
  },
  "name": "Faculté de Droit et des Sciences Politiques de Tunis"
},
{
  "_id": {
    "$oid": "64ef55ed9134d0297553a4f3"
  },
  "name": "Faculté des Sciences Economique et de Gestion de Tunis"
},
{
  "_id": {
    "$oid": "64ef55ed9134d0297553a4f4"
  },
  "name": "Faculté des sciences de tunis"
},
{
  "_id": {
    "$oid": "64ef55ed9134d0297553a4f5"
  },
  "name": "Faculté des sciences Tunis"
},
{
  "_id": {
    "$oid": "64ef55ed9134d0297553a4f6"
  },
  "name": "Faculté de Médecine de Tunis"
},
{
  "_id": {
    "$oid": "64ef55ed9134d0297553a4f7"
  },
  "name": "Ecole Nationale d'Ingénieurs de Tunis"
},
{
  "_id": {
    "$oid": "64ef55ed9134d0297553a4f8"
  },
  "name": "Ecole Nationale Supérieure d'ingénieurs de Tunis"
},
{
  "_id": {
    "$oid": "64ef55ed9134d0297553a4f9"
  },
  "name": "National School of Engineers of Tunis"
},
{
  "_id": {
    "$oid": "64ef55ed9134d0297553a4fa"
  },
  "name": "Institut Bourguiba des Langues Vivantes"
},
{
  "_id": {
    "$oid": "64ef55ed9134d0297553a4fb"
  },
  "name": "Institut Préparatoire aux Etudes d'Ingénieurs d'El Manar"
},
{
  "_id": {
    "$oid": "64ef55ed9134d0297553a4fc"
  },
  "name": "Institut Supérieur des Sciences Biologiques Appliquées"
},
{
  "_id": {
    "$oid": "64ef55ed9134d0297553a4fd"
  },
  "name": "Institut Supérieur d'Informatique"
},
{
  "_id": {
    "$oid": "64ef55ed9134d0297553a4fe"
  },
  "name": "Institute of computer science"
},
{
  "_id": {
    "$oid": "64ef55ed9134d0297553a4ff"
  },
  "name": "Institut Supérieur des Sciences Humaines de Tunis"
},
{
  "_id": {
    "$oid": "64ef55ed9134d0297553a500"
  },
  "name": "Institut Supérieur des Technologies Médicales"
},
{
  "_id": {
    "$oid": "64ef55ed9134d0297553a501"
  },
  "name": "Ecole Supérieure des Sciences et Techniques de la Santé de Tunis"
},
{
  "_id": {
    "$oid": "64ef55ed9134d0297553a502"
  },
  "name": "Institut Supérieur des Sciences infirmières de Tunis"
},
{
  "_id": {
    "$oid": "64ef55ed9134d0297553a503"
  },
  "name": "Institut Pasteur"
},
{
  "_id": {
    "$oid": "64ef55ed9134d0297553a504"
  },
  "name": "Institut de Recherche Vétérinaire de Tunis"
},
{
  "_id": {
    "$oid": "64ef55ed9134d0297553a505"
  },
  "name": "Faculté de Droit et des Sciences Economiques et Politiques de Sousse"
},
{
  "_id": {
    "$oid": "64ef55ed9134d0297553a506"
  },
  "name": "Faculté de Médecine de Sousse"
},
{
  "_id": {
    "$oid": "64ef55ed9134d0297553a507"
  },
  "name": "Faculté des Lettres et des Sciences Humaines de Sousse"
},
{
  "_id": {
    "$oid": "64ef55ed9134d0297553a508"
  },
  "name": "Institut Supérieur de Finance et de Fiscalité de Sousse"
},
{
  "_id": {
    "$oid": "64ef55ed9134d0297553a509"
  },
  "name": "Institut Supérieur d'Informatique et des Technologies de Communication de Hammam Sousse"
},
{
  "_id": {
    "$oid": "64ef55ed9134d0297553a50a"
  },
  "name": "institut superieur d'informatique et des technologies de communication de hammam sousse"
},
{
  "_id": {
    "$oid": "64ef55ed9134d0297553a50b"
  },
  "name": "Institut Supérieur d'Informatique et des Technologies de Communication"
},
{
  "_id": {
    "$oid": "64ef55ed9134d0297553a50c"
  },
  "name": "Institut Supérieur du Transport et de la Logistique de Sousse"
},
{
  "_id": {
    "$oid": "64ef55ed9134d0297553a50d"
  },
  "name": "Institut Supérieur de Beaux Arts de Sousse"
},
{
  "_id": {
    "$oid": "64ef55ed9134d0297553a50e"
  },
  "name": "Ecole Supérieure des Sciences et Techniques de la Santé de Sousse"
},
{
  "_id": {
    "$oid": "64ef55ed9134d0297553a50f"
  },
  "name": "Institut Supérieur de Gestion de Sousse"
},
{
  "_id": {
    "$oid": "64ef55ed9134d0297553a510"
  },
  "name": "Institut des Hautes Etudes Commerciales de Sousse"
},
{
  "_id": {
    "$oid": "64ef55ed9134d0297553a511"
  },
  "name": "Institut Supérieur de Musique de Sousse"
},
{
  "_id": {
    "$oid": "64ef55ed9134d0297553a512"
  },
  "name": "Institut Supérieur des Sciences Appliquées et de Technologie de Sousse"
},
{
  "_id": {
    "$oid": "64ef55ed9134d0297553a513"
  },
  "name": "Ecole Nationale d’Ingénieurs de Sousse"
},
{
  "_id": {
    "$oid": "64ef55ed9134d0297553a514"
  },
  "name": "Institut Supérieur Agronomique de Chott Mériem"
},
{
  "_id": {
    "$oid": "64ef55ed9134d0297553a515"
  },
  "name": "Institut Supérieur des Sciences infirmières de Sousse"
},
{
  "_id": {
    "$oid": "64ef55ed9134d0297553a516"
  },
  "name": "Ecole Supérieure des Sciences et des technologies de Hammam Sousse"
},
{
  "_id": {
    "$oid": "64ef55ed9134d0297553a517"
  },
  "name": "école supérieure des sciences et de la technologie,  hammam sousse"
},
{
  "_id": {
    "$oid": "64ef55ed9134d0297553a518"
  },
  "name": "école supérieure des sciences et  de la technologie de hammam sousse"
},
{
  "_id": {
    "$oid": "64ef55ed9134d0297553a519"
  },
  "name": "école supérieure des sciences et de la technologie de hammam sousse"
},
{
  "_id": {
    "$oid": "64ef55ed9134d0297553a51a"
  },
  "name": "Faculté des Sciences Economiques et de Gestion de Sfax"
},
{
  "_id": {
    "$oid": "64ef55ed9134d0297553a51b"
  },
  "name": "Faculté des Sciences Economiques et de Gestion Sfax"
},
{
  "_id": {
    "$oid": "64ef55ed9134d0297553a51c"
  },
  "name": "Faculté de Médecine de Sfax"
},
{
  "_id": {
    "$oid": "64ef55ed9134d0297553a51d"
  },
  "name": "Faculté de droit de Sfax"
},
{
  "_id": {
    "$oid": "64ef55ed9134d0297553a51e"
  },
  "name": "ecole nationale d'electronique et des telecommunications de sfax"
},
{
  "_id": {
    "$oid": "64ef55ed9134d0297553a51f"
  },
  "name": "Institut Supérieur des Arts et Métiers de Sfax"
},
{
  "_id": {
    "$oid": "64ef55ed9134d0297553a520"
  },
  "name": "Institut Supérieur d'Electronique et de Communication de Sfax"
},
{
  "_id": {
    "$oid": "64ef55ed9134d0297553a521"
  },
  "name": "Institut Supérieur de Gestion Industrielle de Sfax"
},
{
  "_id": {
    "$oid": "64ef55ed9134d0297553a522"
  },
  "name": "Institut des Hautes Etudes Commerciales de Sfax"
},
{
  "_id": {
    "$oid": "64ef55ed9134d0297553a523"
  },
  "name": "Faculté des Sciences de Sfax"
},
{
  "_id": {
    "$oid": "64ef55ed9134d0297553a524"
  },
  "name": "Ecole Nationale d'Ingénieurs de Sfax"
},
{
  "_id": {
    "$oid": "64ef55ed9134d0297553a525"
  },
  "name": "école nationale d'électronique et des télécommunications de sfax"
},
{
  "_id": {
    "$oid": "64ef55ed9134d0297553a526"
  },
  "name": "Ecole Supérieure de Commerce de Sfax"
},
{
  "_id": {
    "$oid": "64ef55ed9134d0297553a527"
  },
  "name": "Institut Supérieur d'Administration des Affaires de Sfax"
},
{
  "_id": {
    "$oid": "64ef55ed9134d0297553a528"
  },
  "name": "Institut Supérieur d'Informatique et de Multimédia de Sfax"
},
{
  "_id": {
    "$oid": "64ef55ed9134d0297553a529"
  },
  "name": "Institut Supérieur de Musique de Sfax"
},
{
  "_id": {
    "$oid": "64ef55ed9134d0297553a52a"
  },
  "name": "Institut Préparatoire aux Etudes d'Ingénieurs de Sfax"
},
{
  "_id": {
    "$oid": "64ef55ed9134d0297553a52b"
  },
  "name": "Institut Supérieur du Sport et de l'Education Physique de Sfax"
},
{
  "_id": {
    "$oid": "64ef55ed9134d0297553a52c"
  },
  "name": "Institut Supérieur de Biotechnologies de Sfax"
},
{
  "_id": {
    "$oid": "64ef55ed9134d0297553a52d"
  },
  "name": "Faculté des Lettres et Sciences Humaines de Sfax"
},
{
  "_id": {
    "$oid": "64ef55ed9134d0297553a52e"
  },
  "name": "Institut Zitouna de Sfax"
},
{
  "_id": {
    "$oid": "64ef55ed9134d0297553a52f"
  },
  "name": "Ecole Supérieure des Sciences et Techniques de la Santé de Sfax"
},
{
  "_id": {
    "$oid": "64ef55ed9134d0297553a530"
  },
  "name": "Institut Supérieur des Sciences infirmières de Sfax"
},
{
  "_id": {
    "$oid": "64ef55ed9134d0297553a531"
  },
  "name": "Faculté des Lettres, des Arts et des Humanités de la Manouba"
},
{
  "_id": {
    "$oid": "64ef55ed9134d0297553a532"
  },
  "name": "Ecole Supérieure des Sciences et Technologies du Design"
},
{
  "_id": {
    "$oid": "64ef55ed9134d0297553a533"
  },
  "name": "Ecole Supérieure de Commerce de Tunis"
},
{
  "_id": {
    "$oid": "64ef55ed9134d0297553a534"
  },
  "name": "Ecole Supérieure de Commerce Electronique de la Manouba"
},
{
  "_id": {
    "$oid": "64ef55ed9134d0297553a535"
  },
  "name": "Ecole Nationale des Sciences de l'Informatique"
},
{
  "_id": {
    "$oid": "64ef55ed9134d0297553a536"
  },
  "name": "Institut Supérieur des Arts du Multimédia de la Manouba"
},
{
  "_id": {
    "$oid": "64ef55ed9134d0297553a537"
  },
  "name": "Institut Supérieur de Comptabilité et d'Administration des Entreprises"
},
{
  "_id": {
    "$oid": "64ef55ed9134d0297553a538"
  },
  "name": "Institut Supérieur de Biotechnologie de Sidi Thabet"
},
{
  "_id": {
    "$oid": "64ef55ed9134d0297553a539"
  },
  "name": "Institut Supérieur de Documentation de Tunis"
},
{
  "_id": {
    "$oid": "64ef55ed9134d0297553a53a"
  },
  "name": "Institut de Presse et des Sciences de l'Information"
},
{
  "_id": {
    "$oid": "64ef55ed9134d0297553a53b"
  },
  "name": "Ecole Nationale de Médecine Vétérinaire de Sidi Thabet"
},
{
  "_id": {
    "$oid": "64ef55ed9134d0297553a53c"
  },
  "name": "Institut Supérieur du Sport et de l'Education Physique de Ksar Saïd"
},
{
  "_id": {
    "$oid": "64ef55ed9134d0297553a53d"
  },
  "name": "Institut Supérieur de Promotion des Handicapés de Ksar Saïd"
},
{
  "_id": {
    "$oid": "64ef55ed9134d0297553a53e"
  },
  "name": "Institut Supérieur de l'Histoire de la Tunisie Contemporaine"
},
{
  "_id": {
    "$oid": "64ef55ed9134d0297553a53f"
  },
  "name": "Faculté des Sciences de Monastir"
},
{
  "_id": {
    "$oid": "64ef55ed9134d0297553a540"
  },
  "name": "Faculté de Médecine de Monastir"
},
{
  "_id": {
    "$oid": "64ef55ed9134d0297553a541"
  },
  "name": "Institut Supérieur d'Informatique et de Mathématiques de Monastir"
},
{
  "_id": {
    "$oid": "64ef55ed9134d0297553a542"
  },
  "name": "Faculté de Médecine Dentaire de Monastir"
},
{
  "_id": {
    "$oid": "64ef55ed9134d0297553a543"
  },
  "name": "Faculté de Pharmacie de Monastir"
},
{
  "_id": {
    "$oid": "64ef55ed9134d0297553a544"
  },
  "name": "Faculté des Sciences Economiques et de Gestion de Mahdia"
},
{
  "_id": {
    "$oid": "64ef55ed9134d0297553a545"
  },
  "name": "Ecole Nationale d'Ingénieurs de Monastir"
},
{
  "_id": {
    "$oid": "64ef55ed9134d0297553a546"
  },
  "name": "institut préparatoire aux études d'ingénieur de monastir"
},
{
  "_id": {
    "$oid": "64ef55ed9134d0297553a547"
  },
  "name": "Institut Supérieur de Biotechnologie de Monastir"
},
{
  "_id": {
    "$oid": "64ef55ed9134d0297553a548"
  },
  "name": "Institut Préparatoire aux Etudes d'Ingénieurs de Monastir"
},
{
  "_id": {
    "$oid": "64ef55ed9134d0297553a549"
  },
  "name": "Ecole Supérieure des Sciences et Techniques de la Santé de Monastir"
},
{
  "_id": {
    "$oid": "64ef55ed9134d0297553a54a"
  },
  "name": "Institut Supérieur des Etudes Appliquées en Humanités de Mahdia"
},
{
  "_id": {
    "$oid": "64ef55ed9134d0297553a54b"
  },
  "name": "Institut Supérieur des Métiers de la Mode de Monastir"
},
{
  "_id": {
    "$oid": "64ef55ed9134d0297553a54c"
  },
  "name": "Institut Supérieur d'Informatique de Mahdia"
},
{
  "_id": {
    "$oid": "64ef55ed9134d0297553a54d"
  },
  "name": "institut superieur d'informatique de mahdia"
},
{
  "_id": {
    "$oid": "64ef55ed9134d0297553a54e"
  },
  "name": "Institut Supérieur des Arts et Métiers de Mahdia"
},
{
  "_id": {
    "$oid": "64ef55ed9134d0297553a54f"
  },
  "name": "Institut Supérieur des Sciences Appliquées et de Technologie de Mahdia"
},
{
  "_id": {
    "$oid": "64ef55ed9134d0297553a550"
  },
  "name": "Institut Supérieur des Langues Appliquées aux Affaires et au Tourisme de Moknine"
},
{
  "_id": {
    "$oid": "64ef55ed9134d0297553a551"
  },
  "name": "Institut Supérieur de Théologie de Tunis"
},
{
  "_id": {
    "$oid": "64ef55ed9134d0297553a552"
  },
  "name": "Institut Supérieur de Civilisation Islamique de Tunis"
},
{
  "_id": {
    "$oid": "64ef55ed9134d0297553a553"
  },
  "name": "Centre de Études Islamiques de Kairouan"
},
{
  "_id": {
    "$oid": "64ef55ed9134d0297553a554"
  },
  "name": "Faculté des Sciences de Gafsa"
},
{
  "_id": {
    "$oid": "64ef55ed9134d0297553a555"
  },
  "name": "Institut Supérieur des Etudes Appliquées en Humanités de Gafsa"
},
{
  "_id": {
    "$oid": "64ef55ed9134d0297553a556"
  },
  "name": "Institut Supérieur d'Administration des Entreprises de Gafsa"
},
{
  "_id": {
    "$oid": "64ef55ed9134d0297553a557"
  },
  "name": "Institut Supérieur des Sciences Appliquées et de Technologie de Gafsa"
},
{
  "_id": {
    "$oid": "64ef55ed9134d0297553a558"
  },
  "name": "Institut Supérieur d'Arts et Métiers de Gafsa"
},
{
  "_id": {
    "$oid": "64ef55ed9134d0297553a559"
  },
  "name": "Institut Supérieur des Sciences et des Technologies de l’énergie de Gafsa"
},
{
  "_id": {
    "$oid": "64ef55ed9134d0297553a55a"
  },
  "name": "Institut Supérieur des Etudes Appliquées en Humanités de Tozeur"
},
{
  "_id": {
    "$oid": "64ef55ed9134d0297553a55b"
  },
  "name": "Institut Préparatoire aux Etudes d’Ingénieur de Gafsa"
},
{
  "_id": {
    "$oid": "64ef55ed9134d0297553a55c"
  },
  "name": "Institut Supérieur du Sport et de l’Education Physique de Gafsa"
},
{
  "_id": {
    "$oid": "64ef55ed9134d0297553a55d"
  },
  "name": "Institut Supérieur des Etudes Technologiques de Sfax"
},
{
  "_id": {
    "$oid": "64ef55ed9134d0297553a55e"
  },
  "name": "Institut Supérieur des Etudes Technologiques de Kebili"
},
{
  "_id": {
    "$oid": "64ef55ed9134d0297553a55f"
  },
  "name": "Institut Supérieur des Etudes Technologiques de Gabès"
},
{
  "_id": {
    "$oid": "64ef55ed9134d0297553a560"
  },
  "name": "Institut Supérieur des Etudes Technologiques de Djerba"
},
{
  "_id": {
    "$oid": "64ef55ed9134d0297553a561"
  },
  "name": "Institut Supérieur des Etudes Technologiques de Kef"
},
{
  "_id": {
    "$oid": "64ef55ed9134d0297553a562"
  },
  "name": "Institut Supérieur des Etudes Technologiques de Zaghouan"
},
{
  "_id": {
    "$oid": "64ef55ed9134d0297553a563"
  },
  "name": "Institut Supérieur des Etudes Technologiques de Sousse"
},
{
  "_id": {
    "$oid": "64ef55ed9134d0297553a564"
  },
  "name": "Institut Supérieur des Etudes Technologiques de Mahdia"
},
{
  "_id": {
    "$oid": "64ef55ed9134d0297553a565"
  },
  "name": "Institut Supérieur des Etudes Technologiques de Siliana"
},
{
  "_id": {
    "$oid": "64ef55ed9134d0297553a566"
  },
  "name": "Institut Supérieur des Etudes Technologiques de Radès"
},
{
  "_id": {
    "$oid": "64ef55ed9134d0297553a567"
  },
  "name": "Institut Supérieur des Etudes Technologiques de Nabeul"
},
{
  "_id": {
    "$oid": "64ef55ed9134d0297553a568"
  },
  "name": "Institut Supérieur des Etudes Technologiques de Sidi Bouzid"
},
{
  "_id": {
    "$oid": "64ef55ed9134d0297553a569"
  },
  "name": "Institut Supérieur des Etudes Technologiques en Communications (El Ghazala)"
},
{
  "_id": {
    "$oid": "64ef55ed9134d0297553a56a"
  },
  "name": "Institut Supérieur des Etudes Technologiques de Kairouan"
},
{
  "_id": {
    "$oid": "64ef55ed9134d0297553a56b"
  },
  "name": "Institut Supérieur des Etudes Technologiques de Gafsa"
},
{
  "_id": {
    "$oid": "64ef55ed9134d0297553a56c"
  },
  "name": "Institut Supérieur des Etudes Technologiques de Béja"
},
{
  "_id": {
    "$oid": "64ef55ed9134d0297553a56d"
  },
  "name": "Institut Supérieur des Etudes Technologiques de Charguia"
},
{
  "_id": {
    "$oid": "64ef55ed9134d0297553a56e"
  },
  "name": "Institut Supérieur des Etudes Technologiques de Jendouba"
},
{
  "_id": {
    "$oid": "64ef55ed9134d0297553a56f"
  },
  "name": "Institut Supérieur des Etudes Technologiques de Kasserine"
},
{
  "_id": {
    "$oid": "64ef55ed9134d0297553a570"
  },
  "name": "Institut Supérieur des Etudes Technologiques de Ksar Hellal"
},
{
  "_id": {
    "$oid": "64ef55ed9134d0297553a571"
  },
  "name": "Institut Supérieur des Etudes Technologiques de Tataouine"
},
{
  "_id": {
    "$oid": "64ef55ed9134d0297553a572"
  },
  "name": "Institut Supérieur des Etudes Technologiques de Tozeur"
},
{
  "_id": {
    "$oid": "64ef55ed9134d0297553a573"
  },
  "name": "Institut Supérieur des Etudes Technologiques de Bizerte"
},
{
  "_id": {
    "$oid": "64ef55ed9134d0297553a574"
  },
  "name": "Institut supérieur des Etudes Technologiques de Médenine"
},
{
  "_id": {
    "$oid": "64ef55ed9134d0297553a575"
  },
  "name": "Faculté des Sciences Juridiques, Economiques et de Gestion de Jendouba"
},
{
  "_id": {
    "$oid": "64ef55ed9134d0297553a576"
  },
  "name": "Institut Supérieur des Etudes Appliquées en Humanités du Kef"
},
{
  "_id": {
    "$oid": "64ef55ed9134d0297553a577"
  },
  "name": "Institut Supérieur des Langues Appliquées et d'Informatique de Béja"
},
{
  "_id": {
    "$oid": "64ef55ed9134d0297553a578"
  },
  "name": "Institut Supérieur des Sciences Humaines de Jendouba"
},
{
  "_id": {
    "$oid": "64ef55ed9134d0297553a579"
  },
  "name": "Institut Supérieur des Arts et Métiers de Siliana"
},
{
  "_id": {
    "$oid": "64ef55ed9134d0297553a57a"
  },
  "name": "Institut Supérieur de Musique et de Théâtre du Kef"
},
{
  "_id": {
    "$oid": "64ef55ed9134d0297553a57b"
  },
  "name": "Institut Supérieur de l 'Education Physique du Kef"
},
{
  "_id": {
    "$oid": "64ef55ed9134d0297553a57c"
  },
  "name": "Ecole Supérieure d 'Agriculture du Kef"
},
{
  "_id": {
    "$oid": "64ef55ed9134d0297553a57d"
  },
  "name": "Institut Sylvo-Pastoral de Tabarka"
},
{
  "_id": {
    "$oid": "64ef55ed9134d0297553a57e"
  },
  "name": "Ecole Supérieure des Ingénieurs de l'Equipement Rural de Medjez El Bab"
},
{
  "_id": {
    "$oid": "64ef55ed9134d0297553a57f"
  },
  "name": "Institut supérieur de l'informatique du Kef"
},
{
  "_id": {
    "$oid": "64ef55ed9134d0297553a580"
  },
  "name": "Institut supérieur de biotechnologie de Béja"
},
{
  "_id": {
    "$oid": "64ef55ed9134d0297553a581"
  },
  "name": "Institut Supérieur des Sciences infirmières du Kef"
},
{
  "_id": {
    "$oid": "64ef55ed9134d0297553a582"
  },
  "name": "Faculté des Lettres et des Sciences Humaines de Kairouan"
},
{
  "_id": {
    "$oid": "64ef55ed9134d0297553a583"
  },
  "name": "Institut Supérieur des Arts et Métiers de Kairouan"
},
{
  "_id": {
    "$oid": "64ef55ed9134d0297553a584"
  },
  "name": "Institut Supérieur d'Informatique et de Gestion de Kairouan"
},
{
  "_id": {
    "$oid": "64ef55ed9134d0297553a585"
  },
  "name": "Institut Supérieur des Etudes Juridiques et Politiques de Kairouan"
},
{
  "_id": {
    "$oid": "64ef55ed9134d0297553a586"
  },
  "name": "Institut Supérieur des Sciences Appliquées et de Technologie de Kairouan"
},
{
  "_id": {
    "$oid": "64ef55ed9134d0297553a587"
  },
  "name": "Institut Supérieur des Arts et Métiers de Kasserine"
},
{
  "_id": {
    "$oid": "64ef55ed9134d0297553a588"
  },
  "name": "Institut Supérieur des Mathématiques Appliquées et de l'Informatique de Kairouan"
},
{
  "_id": {
    "$oid": "64ef55ed9134d0297553a589"
  },
  "name": "Institut Supérieur des Etudes Appliquées en Sciences Humaines de Sbeïtla"
},
{
  "_id": {
    "$oid": "64ef55ed9134d0297553a58a"
  },
  "name": "Institut Supérieur des Arts et Métiers de Sidi Bouzid"
},
{
  "_id": {
    "$oid": "64ef55ed9134d0297553a58b"
  },
  "name": "Faculté des Sciences de Gabès"
},
{
  "_id": {
    "$oid": "64ef55ed9134d0297553a58c"
  },
  "name": "Ecole Nationale d'Ingénieurs de Gabès"
},
{
  "_id": {
    "$oid": "64ef55ed9134d0297553a58d"
  },
  "name": "Institut Supérieur de Gestion de Gabès"
},
{
  "_id": {
    "$oid": "64ef55ed9134d0297553a58e"
  },
  "name": "Institut Supérieur des Langues de Gabès"
},
{
  "_id": {
    "$oid": "64ef55ed9134d0297553a58f"
  },
  "name": "Institut Supérieur des Arts et Métiers de Gabès"
},
{
  "_id": {
    "$oid": "64ef55ed9134d0297553a590"
  },
  "name": "Institut Supérieur de Biologie Appliquée de Médenine"
},
{
  "_id": {
    "$oid": "64ef55ed9134d0297553a591"
  },
  "name": "Institut Supérieur des Etudes Juridiques de Gabès"
},
{
  "_id": {
    "$oid": "64ef55ed9134d0297553a592"
  },
  "name": "Institut Supérieur d'Informatique et de Multimédia de Gabès"
},
{
  "_id": {
    "$oid": "64ef55ed9134d0297553a593"
  },
  "name": "Institut Supérieur des Sciences Appliquées et de Technologie de Gabès"
},
{
  "_id": {
    "$oid": "64ef55ed9134d0297553a594"
  },
  "name": "Institut Supérieur des Sciences et Techniques des Eaux de Gabès"
},
{
  "_id": {
    "$oid": "64ef55ed9134d0297553a595"
  },
  "name": "Institut Supérieur des Systèmes Industriels de Gabès"
},
{
  "_id": {
    "$oid": "64ef55ed9134d0297553a596"
  },
  "name": "Institut Supérieur des Etudes Appliquées en Humanités de Médenine"
},
{
  "_id": {
    "$oid": "64ef55ed9134d0297553a597"
  },
  "name": "Institut Supérieur d'Informatique de Médenine"
},
{
  "_id": {
    "$oid": "64ef55ed9134d0297553a598"
  },
  "name": "Institut Supérieur des Arts et Métiers de Tataouine"
},
{
  "_id": {
    "$oid": "64ef55ed9134d0297553a599"
  },
  "name": "Institut Supérieur des Sciences infirmières de Gabès"
},
{
  "_id": {
    "$oid": "64ef55ed9134d0297553a59a"
  },
  "name": "EPI digital school "
},
{
  "_id": {
    "$oid": "64ef55ed9134d0297553a59b"
  },
  "name": "Faculté des Sciences Paramédicales et de la Santé"
},
{
  "_id": {
    "$oid": "64ef55ed9134d0297553a59c"
  },
  "name": "Faculté des Lettres, des Arts et des Sciences de la Communication"
},
{
  "_id": {
    "$oid": "64ef55ed9134d0297553a59d"
  },
  "name": "Faculté de Droit et de Gestion"
},
{
  "_id": {
    "$oid": "64ef55ed9134d0297553a59e"
  },
  "name": "Ecole Internationale Supérieure Polytechnique de Tunis"
},
{
  "_id": {
    "$oid": "64ef55ed9134d0297553a59f"
  },
  "name": "Ecole Méditerranéenne Supérieure des Affaires"
},
{
  "_id": {
    "$oid": "64ef55ed9134d0297553a5a0"
  },
  "name": "Ecole Méditerranéenne Supérieure Polytechnique"
},
{
  "_id": {
    "$oid": "64ef55ed9134d0297553a5a1"
  },
  "name": "Ecole Supérieure Internationale de Tunis"
},
{
  "_id": {
    "$oid": "64ef55ed9134d0297553a5a2"
  },
  "name": "Ecole Supérieure Centrale Polytechnique"
},
{
  "_id": {
    "$oid": "64ef55ed9134d0297553a5a3"
  },
  "name": "Ecole Supérieure d'Ingénierie et de Technologie "
},
{
  "_id": {
    "$oid": "64ef55ed9134d0297553a5a4"
  },
  "name": "Ecole Supérieure de Carthage des Sciences et d’Ingénierie"
},
{
  "_id": {
    "$oid": "64ef55ed9134d0297553a5a5"
  },
  "name": "Ecole Supérieure de Carthage de Management"
},
{
  "_id": {
    "$oid": "64ef55ed9134d0297553a5a6"
  },
  "name": "Ecole Supérieure de Droit et de management"
},
{
  "_id": {
    "$oid": "64ef55ed9134d0297553a5a7"
  },
  "name": "Ecole Supérieure de l'Aéronautique et des Technologies"
},
{
  "_id": {
    "$oid": "64ef55ed9134d0297553a5a8"
  },
  "name": "Ecole Supérieure de l'Audiovisuel et du Design"
},
{
  "_id": {
    "$oid": "64ef55ed9134d0297553a5a9"
  },
  "name": "Ecole Supérieure de Technologie et de Management"
},
{
  "_id": {
    "$oid": "64ef55ed9134d0297553a5aa"
  },
  "name": "Ecole Supérieure de Technologies de l'Information et d’Administration des Entreprises"
},
{
  "_id": {
    "$oid": "64ef55ed9134d0297553a5ab"
  },
  "name": "Ecole Supérieure de technologies et d’ingénierie"
},
{
  "_id": {
    "$oid": "64ef55ed9134d0297553a5ac"
  },
  "name": "Ecole Supérieure des Sciences Appliquées et de Management"
},
{
  "_id": {
    "$oid": "64ef55ed9134d0297553a5ad"
  },
  "name": "Ecole Supérieure d’Administration des Affaires et de Droit \" Avicenne»"
},
{
  "_id": {
    "$oid": "64ef55ed9134d0297553a5ae"
  },
  "name": "Ecole Supérieure d’Informatique et d’Administration des Affaires"
},
{
  "_id": {
    "$oid": "64ef55ed9134d0297553a5af"
  },
  "name": "Ecole Supérieure d’ingénierie et de communication"
},
{
  "_id": {
    "$oid": "64ef55ed9134d0297553a5b0"
  },
  "name": "Ecole Supérieure d’Ingénieurs et d’Etudes Technologiques de Tunis"
},
{
  "_id": {
    "$oid": "64ef55ed9134d0297553a5b1"
  },
  "name": "Ecole Supérieure Polytechnique Ibn Khaldoun"
},
{
  "_id": {
    "$oid": "64ef55ed9134d0297553a5b2"
  },
  "name": "Ecole Supérieure Law and Business School"
},
{
  "_id": {
    "$oid": "64ef55ed9134d0297553a5b3"
  },
  "name": "Ecole Supérieure Maghrébine des Sciences et Technologies"
},
{
  "_id": {
    "$oid": "64ef55ed9134d0297553a5b4"
  },
  "name": "Faculté Méditerranéenne des Sciences Informatiques, d’Economie et de Gestion de Tunis"
},
{
  "_id": {
    "$oid": "64ef55ed9134d0297553a5b5"
  },
  "name": "Faculté de Droit, d’Economie et de Gestion"
},
{
  "_id": {
    "$oid": "64ef55ed9134d0297553a5b6"
  },
  "name": "Faculté de Montplaisir"
},
{
  "_id": {
    "$oid": "64ef55ed9134d0297553a5b7"
  },
  "name": "Faculté des Sciences de Gestion et de Technologie à Mégrine"
},
{
  "_id": {
    "$oid": "64ef55ed9134d0297553a5b8"
  },
  "name": "Faculté des Sciences de la santé de Tunis"
},
{
  "_id": {
    "$oid": "64ef55ed9134d0297553a5b9"
  },
  "name": "Faculté des Sciences Juridiques, Sociales, Economiques et de Gestion"
},
{
  "_id": {
    "$oid": "64ef55ed9134d0297553a5ba"
  },
  "name": "Faculté Ibn Khaldoun de Droit, des Sciences Economiques et de Gestion"
},
{
  "_id": {
    "$oid": "64ef55ed9134d0297553a5bb"
  },
  "name": "Institut International Supérieur des Etudes Numériques et Audiovisuelles"
},
{
  "_id": {
    "$oid": "64ef55ed9134d0297553a5bc"
  },
  "name": "Institut des Hautes Etudes de Tunis"
},
{
  "_id": {
    "$oid": "64ef55ed9134d0297553a5bd"
  },
  "name": "Institut Supérieur des Sciences Paramédicales \" Mahmoud Materi\""
},
{
  "_id": {
    "$oid": "64ef55ed9134d0297553a5be"
  },
  "name": "Institut Supérieur d’administration des Entreprises"
},
{
  "_id": {
    "$oid": "64ef55ed9134d0297553a5bf"
  },
  "name": "Institut Supérieur Méditerranéen de Technologie"
},
{
  "_id": {
    "$oid": "64ef55ed9134d0297553a5c0"
  },
  "name": "Institut Supérieur Polytechnique"
},
{
  "_id": {
    "$oid": "64ef55ed9134d0297553a5c1"
  },
  "name": "Institut Supérieur Tunis Dauphine"
},
{
  "_id": {
    "$oid": "64ef55ed9134d0297553a5c2"
  },
  "name": "Ecole Supérieure Polytechnique Privée de Sousse"
},
{
  "_id": {
    "$oid": "64ef55ed9134d0297553a5c3"
  },
  "name": "Ecole Supérieure Internationale Privée de Management de Sousse"
},
{
  "_id": {
    "$oid": "64ef55ed9134d0297553a5c4"
  },
  "name": "Ecole Supérieure Privée de Technologie, d’Informatique et de Gestion de Sousse"
},
{
  "_id": {
    "$oid": "64ef55ed9134d0297553a5c5"
  },
  "name": "Ecole Supérieure Privée d’Economie et de Gestion de Sousse"
},
{
  "_id": {
    "$oid": "64ef55ed9134d0297553a5c6"
  },
  "name": "Ecole Supérieure Privée d’Ingénierie et de Technologie appliquée- Sousse"
},
{
  "_id": {
    "$oid": "64ef55ed9134d0297553a5c7"
  },
  "name": "Ecole Supérieure Privée d’Ingénierie, des Sciences et de Technologie de Sousse"
},
{
  "_id": {
    "$oid": "64ef55ed9134d0297553a5c8"
  },
  "name": "Ecole Supérieure Privée d’Ingénieurs de Sousse"
},
{
  "_id": {
    "$oid": "64ef55ed9134d0297553a5c9"
  },
  "name": "école supérieure privée d'ingénierie et de technologies "
},
{
  "_id": {
    "$oid": "64ef55ed9134d0297553a5ca"
  },
  "name": "Faculté Privée de Gestion et des Sciences de l’Administration de Sousse"
},
{
  "_id": {
    "$oid": "64ef55ed9134d0297553a5cb"
  },
  "name": "Institut Privé des Hautes Etudes de Sousse"
},
{
  "_id": {
    "$oid": "64ef55ed9134d0297553a5cc"
  },
  "name": "Institut Supérieur Privé Des Sciences Commerciales Et Des Affaires"
},
{
  "_id": {
    "$oid": "64ef55ed9134d0297553a5cd"
  },
  "name": "Institut Supérieur Privé des Sciences de la Santé de Sousse"
},
{
  "_id": {
    "$oid": "64ef55ed9134d0297553a5ce"
  },
  "name": "Institut Supérieur Privé des Sciences Infirmières \"EL AMED\""
},
{
  "_id": {
    "$oid": "64ef55ed9134d0297553a5cf"
  },
  "name": "Institut Supérieur Privé des Sciences Infirmières \"Etoile de formation\""
},
{
  "_id": {
    "$oid": "64ef55ed9134d0297553a5d0"
  },
  "name": "Institut Supérieur Privé des Sciences Infirmières de Sousse"
},
{
  "_id": {
    "$oid": "64ef55ed9134d0297553a5d1"
  },
  "name": "Ecole Supérieure Internationale Privée de Technologie - Sfax"
},
{
  "_id": {
    "$oid": "64ef55ed9134d0297553a5d2"
  },
  "name": "Ecole Internationale Supérieure Privée des Affaires"
},
{
  "_id": {
    "$oid": "64ef55ed9134d0297553a5d3"
  },
  "name": "Ecole Supérieure Privée des Etudes Administratives et Commerciales de Sfax"
},
{
  "_id": {
    "$oid": "64ef55ed9134d0297553a5d4"
  },
  "name": "Ecole Supérieure Polytechnique Internationale Privée de Sfax"
},
{
  "_id": {
    "$oid": "64ef55ed9134d0297553a5d5"
  },
  "name": "Faculté Privée des Sciences Paramédicales de Sfax"
},
{
  "_id": {
    "$oid": "64ef55ed9134d0297553a5d6"
  },
  "name": "Institut Supérieur Polytechnique Privé des Sciences Avancées du Sud "
},
{
  "_id": {
    "$oid": "64ef55ed9134d0297553a5d7"
  },
  "name": "Faculté Privée des sciences de l’informatique et de management de Nabeul"
},
{
  "_id": {
    "$oid": "64ef55ed9134d0297553a5d8"
  },
  "name": "Ecole Méditerranéenne Supérieure Privée des Sciences Informatiques, d’Economie et de Gestion de Nabeul"
},
{
  "_id": {
    "$oid": "64ef55ed9134d0297553a5d9"
  },
  "name": "Ecole Supérieure Privée des Technologies de l’Information et de Management de Nabeul"
},
{
  "_id": {
    "$oid": "64ef55ed9134d0297553a5da"
  },
  "name": "Ecole Supérieure Privée d’ingénieurs de Monastir"
},
{
  "_id": {
    "$oid": "64ef55ed9134d0297553a5db"
  },
  "name": "Ecole Supérieure Polytechnique Privée de Monastir"
},
{
  "_id": {
    "$oid": "64ef55ed9134d0297553a5dc"
  },
  "name": "Ecole Supérieure Privée des Sciences Appliquées et de Technologie de Gabès (université technologique privée de gabès - Utech)"
},
{
  "_id": {
    "$oid": "64ef55ed9134d0297553a5dd"
  },
  "name": "Ecole Supérieure Privée d’ingénieurs de Gafsa : ESIP Gafsa"
},
{
  "_id": {
    "$oid": "64ef55ed9134d0297553a5de"
  },
  "name": "Institut Supérieur Privé des Sciences Infirmières de Kairouan: ISPSIK"
},
{
  "_id": {
    "$oid": "64ef55ed9134d0297553a5df"
  },
  "name": "Faculty of Human and Social Sciences of Tunis"
},
{
  "_id": {
    "$oid": "64ef55ed9134d0297553a5e0"
  },
  "name": "Higher School of Economics and Commercial Sciences of Tunis"
},
{
  "_id": {
    "$oid": "64ef55ed9134d0297553a5e1"
  },
  "name": "École Normale Supérieure"
},
{
  "_id": {
    "$oid": "64ef55ed9134d0297553a5e2"
  },
  "name": "Higher School of Sciences and Techniques of Tunis"
},
{
  "_id": {
    "$oid": "64ef55ed9134d0297553a5e3"
  },
  "name": "Preparatory Institute for Engineering Studies of Tunis"
},
{
  "_id": {
    "$oid": "64ef55ed9134d0297553a5e4"
  },
  "name": "Preparatory Institute for Literary Studies and Human Sciences of Tunis"
},
{
  "_id": {
    "$oid": "64ef55ed9134d0297553a5e5"
  },
  "name": "Higher Institute of Management of Tunis"
},
{
  "_id": {
    "$oid": "64ef55ed9134d0297553a5e6"
  },
  "name": "Higher Institute of Education and Continuing Education"
},
{
  "_id": {
    "$oid": "64ef55ed9134d0297553a5e7"
  },
  "name": "Higher Institute of Fine Arts of Tunis"
},
{
  "_id": {
    "$oid": "64ef55ed9134d0297553a5e8"
  },
  "name": "Higher Institute of Music"
},
{
  "_id": {
    "$oid": "64ef55ed9134d0297553a5e9"
  },
  "name": "Higher Institute of Dramatic Art"
},
{
  "_id": {
    "$oid": "64ef55ed9134d0297553a5ea"
  },
  "name": "Higher Institute of Cultural Sciences and Heritage Professions of Tunis"
},
{
  "_id": {
    "$oid": "64ef55ed9134d0297553a5eb"
  },
  "name": "Higher Institute of Applied Studies in Humanities of Tunis"
},
{
  "_id": {
    "$oid": "64ef55ed9134d0297553a5ec"
  },
  "name": "Higher Institute of Animation for Youth and Culture"
},
{
  "_id": {
    "$oid": "64ef55ed9134d0297553a5ed"
  },
  "name": "Higher Institute of Applied Studies in Humanities of Zaghouan"
},
{
  "_id": {
    "$oid": "64ef55ed9134d0297553a5ee"
  },
  "name": "National Heritage Institute"
},
{
  "_id": {
    "$oid": "64ef55ed9134d0297553a5ef"
  },
  "name": "Tunis Business School"
},
{
  "_id": {
    "$oid": "64ef55ed9134d0297553a5f0"
  },
  "name": "Faculty of Law and Political Sciences of Tunis"
},
{
  "_id": {
    "$oid": "64ef55ed9134d0297553a5f1"
  },
  "name": "Faculty of Economics and Management of Tunis"
},
{
  "_id": {
    "$oid": "64ef55ed9134d0297553a5f2"
  },
  "name": "Faculty of Sciences of Tunis"
},
{
  "_id": {
    "$oid": "64ef55ed9134d0297553a5f3"
  },
  "name": "Faculty of sciences Tunis"
},
{
  "_id": {
    "$oid": "64ef55ed9134d0297553a5f4"
  },
  "name": "Faculty of Medicine of Tunis"
},
{
  "_id": {
    "$oid": "64ef55ed9134d0297553a5f5"
  },
  "name": "National Engineers School of Tunis"
},
{
  "_id": {
    "$oid": "64ef55ed9134d0297553a5f6"
  },
  "name": "Bourguiba Institute of Modern Languages"
},
{
  "_id": {
    "$oid": "64ef55ed9134d0297553a5f7"
  },
  "name": "Preparatory Institute for Engineering Studies of El Manar"
},
{
  "_id": {
    "$oid": "64ef55ed9134d0297553a5f8"
  },
  "name": "Higher Institute of Applied Biological Sciences"
},
{
  "_id": {
    "$oid": "64ef55ed9134d0297553a5f9"
  },
  "name": "Higher Institute of Computer Science of El Manar"
},
{
  "_id": {
    "$oid": "64ef55ed9134d0297553a5fa"
  },
  "name": "Higher Institute of Human Sciences of Tunis"
},
{
  "_id": {
    "$oid": "64ef55ed9134d0297553a5fb"
  },
  "name": "Higher Institute of Medical Technologies"
},
{
  "_id": {
    "$oid": "64ef55ed9134d0297553a5fc"
  },
  "name": "Higher School of Health Sciences and Techniques of Tunis"
},
{
  "_id": {
    "$oid": "64ef55ed9134d0297553a5fd"
  },
  "name": "Higher Institute of Nursing Sciences of Tunis"
},
{
  "_id": {
    "$oid": "64ef55ed9134d0297553a5fe"
  },
  "name": "Pastor Institute"
},
{
  "_id": {
    "$oid": "64ef55ed9134d0297553a5ff"
  },
  "name": "Tunis Veterinary Research Institute"
},
{
  "_id": {
    "$oid": "64ef55ed9134d0297553a600"
  },
  "name": "Faculty of Law and Economic and Political Sciences of Sousse"
},
{
  "_id": {
    "$oid": "64ef55ed9134d0297553a601"
  },
  "name": "Faculty of Medicine of Sousse"
},
{
  "_id": {
    "$oid": "64ef55ed9134d0297553a602"
  },
  "name": "Faculty of Letters and Human Sciences of Sousse"
},
{
  "_id": {
    "$oid": "64ef55ed9134d0297553a603"
  },
  "name": "Higher Institute of Finance and Taxation of Sousse"
},
{
  "_id": {
    "$oid": "64ef55ed9134d0297553a604"
  },
  "name": "Higher Institute of Computer Science and Communication Technologies of Hammam Sousse"
},
{
  "_id": {
    "$oid": "64ef55ed9134d0297553a605"
  },
  "name": "Higher Institute of Transport and Logistics of Sousse"
},
{
  "_id": {
    "$oid": "64ef55ed9134d0297553a606"
  },
  "name": "Higher Institute of Fine Arts of Sousse"
},
{
  "_id": {
    "$oid": "64ef55ed9134d0297553a607"
  },
  "name": "Higher School of Health Sciences and Techniques of Sousse"
},
{
  "_id": {
    "$oid": "64ef55ed9134d0297553a608"
  },
  "name": "Higher Institute of Management of Sousse"
},
{
  "_id": {
    "$oid": "64ef55ed9134d0297553a609"
  },
  "name": "Institute of Higher Commercial Studies of Sousse"
},
{
  "_id": {
    "$oid": "64ef55ed9134d0297553a60a"
  },
  "name": "Higher Institute of Music of Sousse"
},
{
  "_id": {
    "$oid": "64ef55ed9134d0297553a60b"
  },
  "name": "Higher Institute of Applied Sciences and Technology of Sousse"
},
{
  "_id": {
    "$oid": "64ef55ed9134d0297553a60c"
  },
  "name": "institute of applied science and technology of sousse"
},
{
  "_id": {
    "$oid": "64ef55ed9134d0297553a60d"
  },
  "name": "National School of Engineers of Sousse"
},
{
  "_id": {
    "$oid": "64ef55ed9134d0297553a60e"
  },
  "name": "Higher Agronomic Institute of Chott Meriem"
},
{
  "_id": {
    "$oid": "64ef55ed9134d0297553a60f"
  },
  "name": "Higher Institute of Nursing Sciences of Sousse"
},
{
  "_id": {
    "$oid": "64ef55ed9134d0297553a610"
  },
  "name": "Higher School of Science and Technology of Hammam Sousse"
},
{
  "_id": {
    "$oid": "64ef55ed9134d0297553a611"
  },
  "name": "Faculty of Economics and Management of Sfax"
},
{
  "_id": {
    "$oid": "64ef55ed9134d0297553a612"
  },
  "name": "faculty of economics and management sfax"
},
{
  "_id": {
    "$oid": "64ef55ed9134d0297553a613"
  },
  "name": "Faculty of Medicine of Sfax"
},
{
  "_id": {
    "$oid": "64ef55ed9134d0297553a614"
  },
  "name": "Faculty of Law of Sfax"
},
{
  "_id": {
    "$oid": "64ef55ed9134d0297553a615"
  },
  "name": "Higher Institute of Arts and Crafts of Sfax"
},
{
  "_id": {
    "$oid": "64ef55ed9134d0297553a616"
  },
  "name": "Higher Institute of Electronics and Communication of Sfax"
},
{
  "_id": {
    "$oid": "64ef55ed9134d0297553a617"
  },
  "name": "Higher Institute of Industrial Management of Sfax"
},
{
  "_id": {
    "$oid": "64ef55ed9134d0297553a618"
  },
  "name": "Institute of Higher Commercial Studies of Sfax"
},
{
  "_id": {
    "$oid": "64ef55ed9134d0297553a619"
  },
  "name": "Faculty of Sciences of Sfax"
},
{
  "_id": {
    "$oid": "64ef55ed9134d0297553a61a"
  },
  "name": "Faculty of Sciences Sfax"
},
{
  "_id": {
    "$oid": "64ef55ed9134d0297553a61b"
  },
  "name": "National School of Engineers of Sfax"
},
{
  "_id": {
    "$oid": "64ef55ed9134d0297553a61c"
  },
  "name": "Sfax Business School"
},
{
  "_id": {
    "$oid": "64ef55ed9134d0297553a61d"
  },
  "name": "Higher Institute of Business Administration of Sfax"
},
{
  "_id": {
    "$oid": "64ef55ed9134d0297553a61e"
  },
  "name": "Higher Institute of Computer Science and Multimedia of Sfax"
},
{
  "_id": {
    "$oid": "64ef55ed9134d0297553a61f"
  },
  "name": "Higher Institute of Music of Sfax"
},
{
  "_id": {
    "$oid": "64ef55ed9134d0297553a620"
  },
  "name": "Preparatory Institute for Engineering Studies of Sfax"
},
{
  "_id": {
    "$oid": "64ef55ed9134d0297553a621"
  },
  "name": "Higher Institute of Sport and Physical Education of Sfax"
},
{
  "_id": {
    "$oid": "64ef55ed9134d0297553a622"
  },
  "name": "Higher Institute of Biotechnology of Sfax"
},
{
  "_id": {
    "$oid": "64ef55ed9134d0297553a623"
  },
  "name": "Faculty of Letters and Human Sciences of Sfax"
},
{
  "_id": {
    "$oid": "64ef55ed9134d0297553a624"
  },
  "name": "Zitouna Institute of Sfax"
},
{
  "_id": {
    "$oid": "64ef55ed9134d0297553a625"
  },
  "name": "Higher School of Health Sciences and Techniques of Sfax"
},
{
  "_id": {
    "$oid": "64ef55ed9134d0297553a626"
  },
  "name": "Higher Institute of Nursing Sciences of Sfax"
},
{
  "_id": {
    "$oid": "64ef55ed9134d0297553a627"
  },
  "name": "Faculty of Letters, Arts and Humanities of Manouba"
},
{
  "_id": {
    "$oid": "64ef55ed9134d0297553a628"
  },
  "name": "School of Design Sciences and Technologies"
},
{
  "_id": {
    "$oid": "64ef55ed9134d0297553a629"
  },
  "name": "Tunis Business School"
},
{
  "_id": {
    "$oid": "64ef55ed9134d0297553a62a"
  },
  "name": "Higher School of Electronic Commerce of Manouba"
},
{
  "_id": {
    "$oid": "64ef55ed9134d0297553a62b"
  },
  "name": "National School of Computer Science"
},
{
  "_id": {
    "$oid": "64ef55ed9134d0297553a62c"
  },
  "name": "Higher Institute of Multimedia Arts of Manouba"
},
{
  "_id": {
    "$oid": "64ef55ed9134d0297553a62d"
  },
  "name": "Higher Institute of Accounting and Business Administration"
},
{
  "_id": {
    "$oid": "64ef55ed9134d0297553a62e"
  },
  "name": "Higher Institute of Biotechnology of Sidi Thabet"
},
{
  "_id": {
    "$oid": "64ef55ed9134d0297553a62f"
  },
  "name": "Higher Institute of Documentation of Tunis"
},
{
  "_id": {
    "$oid": "64ef55ed9134d0297553a630"
  },
  "name": "Institute of Press and Information Sciences"
},
{
  "_id": {
    "$oid": "64ef55ed9134d0297553a631"
  },
  "name": "National School of Veterinary Medicine of Sidi Thabet"
},
{
  "_id": {
    "$oid": "64ef55ed9134d0297553a632"
  },
  "name": "Higher Institute of Sport and Physical Education of Ksar Saïd"
},
{
  "_id": {
    "$oid": "64ef55ed9134d0297553a633"
  },
  "name": "Higher Institute for the Promotion of the Disabled of Ksar Saïd"
},
{
  "_id": {
    "$oid": "64ef55ed9134d0297553a634"
  },
  "name": "Higher Institute of the History of Contemporary Tunisia"
},
{
  "_id": {
    "$oid": "64ef55ed9134d0297553a635"
  },
  "name": "Faculty of Sciences of Monastir"
},
{
  "_id": {
    "$oid": "64ef55ed9134d0297553a636"
  },
  "name": "faculty of science monastir"
},
{
  "_id": {
    "$oid": "64ef55ed9134d0297553a637"
  },
  "name": "faculty of sciences monastir"
},
{
  "_id": {
    "$oid": "64ef55ed9134d0297553a638"
  },
  "name": "Faculty of Medicine of Monastir"
},
{
  "_id": {
    "$oid": "64ef55ed9134d0297553a639"
  },
  "name": "Higher Institute of Computer Science and Mathematics of Monastir"
},
{
  "_id": {
    "$oid": "64ef55ed9134d0297553a63a"
  },
  "name": "Faculty of Dental Medicine of Monastir"
},
{
  "_id": {
    "$oid": "64ef55ed9134d0297553a63b"
  },
  "name": "Faculty of Pharmacy of Monastir"
},
{
  "_id": {
    "$oid": "64ef55ed9134d0297553a63c"
  },
  "name": "Faculty of Economics and Management of Mahdia"
},
{
  "_id": {
    "$oid": "64ef55ed9134d0297553a63d"
  },
  "name": "National School of Engineers of Monastir"
},
{
  "_id": {
    "$oid": "64ef55ed9134d0297553a63e"
  },
  "name": "Higher Institute of Biotechnology of Monastir"
},
{
  "_id": {
    "$oid": "64ef55ed9134d0297553a63f"
  },
  "name": "Preparatory Institute for Engineering Studies of Monastir"
},
{
  "_id": {
    "$oid": "64ef55ed9134d0297553a640"
  },
  "name": "Higher School of Health Sciences and Techniques of Monastir"
},
{
  "_id": {
    "$oid": "64ef55ed9134d0297553a641"
  },
  "name": "Higher Institute of Applied Studies in Humanities of Mahdia"
},
{
  "_id": {
    "$oid": "64ef55ed9134d0297553a642"
  },
  "name": "Higher Institute of Fashion Professions of Monastir"
},
{
  "_id": {
    "$oid": "64ef55ed9134d0297553a643"
  },
  "name": "Higher Institute of Computer Science of Mahdia"
},
{
  "_id": {
    "$oid": "64ef55ed9134d0297553a644"
  },
  "name": "Higher Institute of Arts and Crafts of Mahdia"
},
{
  "_id": {
    "$oid": "64ef55ed9134d0297553a645"
  },
  "name": "Higher Institute of Applied Sciences and Technology of Mahdia"
},
{
  "_id": {
    "$oid": "64ef55ed9134d0297553a646"
  },
  "name": "Higher Institute of Languages Applied to Business and Tourism of Moknine"
},
{
  "_id": {
    "$oid": "64ef55ed9134d0297553a647"
  },
  "name": "Higher Institute of Theology of Tunis"
},
{
  "_id": {
    "$oid": "64ef55ed9134d0297553a648"
  },
  "name": "Higher Institute of Islamic Civilization of Tunis"
},
{
  "_id": {
    "$oid": "64ef55ed9134d0297553a649"
  },
  "name": "Center for Islamic Studies of Kairouan"
},
{
  "_id": {
    "$oid": "64ef55ed9134d0297553a64a"
  },
  "name": "Faculty of Sciences of Gafsa"
},
{
  "_id": {
    "$oid": "64ef55ed9134d0297553a64b"
  },
  "name": "Faculty of Sciences Gafsa"
},
{
  "_id": {
    "$oid": "64ef55ed9134d0297553a64c"
  },
  "name": "Higher Institute of Applied Studies in Humanities of Gafsa"
},
{
  "_id": {
    "$oid": "64ef55ed9134d0297553a64d"
  },
  "name": "Higher Institute of Business Administration of Gafsa"
},
{
  "_id": {
    "$oid": "64ef55ed9134d0297553a64e"
  },
  "name": "Higher Institute of Applied Sciences and Technology of Gafsa"
},
{
  "_id": {
    "$oid": "64ef55ed9134d0297553a64f"
  },
  "name": "Higher Institute of Arts and Crafts of Gafsa"
},
{
  "_id": {
    "$oid": "64ef55ed9134d0297553a650"
  },
  "name": "Higher Institute of Energy Sciences and Technologies of Gafsa"
},
{
  "_id": {
    "$oid": "64ef55ed9134d0297553a651"
  },
  "name": "Higher Institute of Applied Studies in Humanities of Tozeur"
},
{
  "_id": {
    "$oid": "64ef55ed9134d0297553a652"
  },
  "name": "Preparatory Institute for Engineering Studies of Gafsa"
},
{
  "_id": {
    "$oid": "64ef55ed9134d0297553a653"
  },
  "name": "Higher Institute of Sport and Physical Education of Gafsa"
},
{
  "_id": {
    "$oid": "64ef55ed9134d0297553a654"
  },
  "name": "Higher Institute of Technological Studies of Sfax"
},
{
  "_id": {
    "$oid": "64ef55ed9134d0297553a655"
  },
  "name": "Higher Institute of Technological Studies of Kebili"
},
{
  "_id": {
    "$oid": "64ef55ed9134d0297553a656"
  },
  "name": "Higher Institute of Technological Studies of Gabes"
},
{
  "_id": {
    "$oid": "64ef55ed9134d0297553a657"
  },
  "name": "Higher Institute of Technological Studies of Djerba"
},
{
  "_id": {
    "$oid": "64ef55ed9134d0297553a658"
  },
  "name": "Higher Institute of Technological Studies of Kef"
},
{
  "_id": {
    "$oid": "64ef55ed9134d0297553a659"
  },
  "name": "Higher Institute of Technological Studies of Zaghouan"
},
{
  "_id": {
    "$oid": "64ef55ed9134d0297553a65a"
  },
  "name": "Higher Institute of Technological Studies of Sousse"
},
{
  "_id": {
    "$oid": "64ef55ed9134d0297553a65b"
  },
  "name": "Higher Institute of Technological Studies of Mahdia"
},
{
  "_id": {
    "$oid": "64ef55ed9134d0297553a65c"
  },
  "name": "Higher Institute of Technological Studies of Siliana"
},
{
  "_id": {
    "$oid": "64ef55ed9134d0297553a65d"
  },
  "name": "Higher Institute of Technological Studies of Rades"
},
{
  "_id": {
    "$oid": "64ef55ed9134d0297553a65e"
  },
  "name": "Higher Institute of Technological Studies of Nabeul"
},
{
  "_id": {
    "$oid": "64ef55ed9134d0297553a65f"
  },
  "name": "Higher Institute of Technological Studies of Sidi Bouzid"
},
{
  "_id": {
    "$oid": "64ef55ed9134d0297553a660"
  },
  "name": "Higher Institute of Technological Studies in Communications (El Ghazala)"
},
{
  "_id": {
    "$oid": "64ef55ed9134d0297553a661"
  },
  "name": "Higher Institute of Technological Studies of Kairouan"
},
{
  "_id": {
    "$oid": "64ef55ed9134d0297553a662"
  },
  "name": "Higher Institute of Technological Studies of Gafsa"
},
{
  "_id": {
    "$oid": "64ef55ed9134d0297553a663"
  },
  "name": "Higher Institute of Technological Studies of Beja"
},
{
  "_id": {
    "$oid": "64ef55ed9134d0297553a664"
  },
  "name": "Higher Institute of Technological Studies of Charguia"
},
{
  "_id": {
    "$oid": "64ef55ed9134d0297553a665"
  },
  "name": "Higher Institute of Technological Studies of Jendouba"
},
{
  "_id": {
    "$oid": "64ef55ed9134d0297553a666"
  },
  "name": "Higher Institute of Technological Studies of Kasserine"
},
{
  "_id": {
    "$oid": "64ef55ed9134d0297553a667"
  },
  "name": "Higher Institute of Technological Studies of Ksar Hellal"
},
{
  "_id": {
    "$oid": "64ef55ed9134d0297553a668"
  },
  "name": "Higher Institute of Technological Studies of Tataouine"
},
{
  "_id": {
    "$oid": "64ef55ed9134d0297553a669"
  },
  "name": "Higher Institute of Technological Studies of Tozeur"
},
{
  "_id": {
    "$oid": "64ef55ed9134d0297553a66a"
  },
  "name": "Higher Institute of Technological Studies of Bizerte"
},
{
  "_id": {
    "$oid": "64ef55ed9134d0297553a66b"
  },
  "name": "Higher Institute of Technological Studies of Medenine"
},
{
  "_id": {
    "$oid": "64ef55ed9134d0297553a66c"
  },
  "name": "Faculty of Legal, Economic and Management Sciences of Jendouba"
},
{
  "_id": {
    "$oid": "64ef55ed9134d0297553a66d"
  },
  "name": "Higher Institute of Applied Studies in Humanities of Kef"
},
{
  "_id": {
    "$oid": "64ef55ed9134d0297553a66e"
  },
  "name": "Higher Institute of Applied Languages and Computer Science of Béja"
},
{
  "_id": {
    "$oid": "64ef55ed9134d0297553a66f"
  },
  "name": "Higher Institute of Human Sciences of Jendouba"
},
{
  "_id": {
    "$oid": "64ef55ed9134d0297553a670"
  },
  "name": "Higher Institute of Arts and Crafts of Siliana"
},
{
  "_id": {
    "$oid": "64ef55ed9134d0297553a671"
  },
  "name": "Higher Institute of Music and Theater of Kef"
},
{
  "_id": {
    "$oid": "64ef55ed9134d0297553a672"
  },
  "name": "Higher Institute of Physical Education of Kef"
},
{
  "_id": {
    "$oid": "64ef55ed9134d0297553a673"
  },
  "name": "Higher School of Agriculture of Kef"
},
{
  "_id": {
    "$oid": "64ef55ed9134d0297553a674"
  },
  "name": "Sylvo-Pastoral Institute of Tabarka"
},
{
  "_id": {
    "$oid": "64ef55ed9134d0297553a675"
  },
  "name": "Higher School of Rural Equipment Engineers of Medjez El Bab"
},
{
  "_id": {
    "$oid": "64ef55ed9134d0297553a676"
  },
  "name": "Higher Institute of Computer Science of Kef"
},
{
  "_id": {
    "$oid": "64ef55ed9134d0297553a677"
  },
  "name": "Higher Institute of Biotechnology of Beja"
},
{
  "_id": {
    "$oid": "64ef55ed9134d0297553a678"
  },
  "name": "Higher Institute of Nursing Sciences of Kef"
},
{
  "_id": {
    "$oid": "64ef55ed9134d0297553a679"
  },
  "name": "Faculty of Letters and Human Sciences of Kairouan"
},
{
  "_id": {
    "$oid": "64ef55ed9134d0297553a67a"
  },
  "name": "Higher Institute of Arts and Crafts of Kairouan"
},
{
  "_id": {
    "$oid": "64ef55ed9134d0297553a67b"
  },
  "name": "Higher Institute of Computer Science and Management of Kairouan"
},
{
  "_id": {
    "$oid": "64ef55ed9134d0297553a67c"
  },
  "name": "Higher Institute of Legal and Political Studies of Kairouan"
},
{
  "_id": {
    "$oid": "64ef55ed9134d0297553a67d"
  },
  "name": "Higher Institute of Applied Sciences and Technology of Kairouan"
},
{
  "_id": {
    "$oid": "64ef55ed9134d0297553a67e"
  },
  "name": "Higher Institute of Arts and Crafts of Kasserine"
},
{
  "_id": {
    "$oid": "64ef55ed9134d0297553a67f"
  },
  "name": "Higher Institute of Applied Mathematics and Computer Science of Kairouan"
},
{
  "_id": {
    "$oid": "64ef55ed9134d0297553a680"
  },
  "name": "Higher Institute of Applied Studies in Human Sciences of Sbeïtla"
},
{
  "_id": {
    "$oid": "64ef55ed9134d0297553a681"
  },
  "name": "Higher Institute of Arts and Crafts of Sidi Bouzid"
},
{
  "_id": {
    "$oid": "64ef55ed9134d0297553a682"
  },
  "name": "Faculty of Sciences of Gabes"
},
{
  "_id": {
    "$oid": "64ef55ed9134d0297553a683"
  },
  "name": "Faculty of Sciences Gabes"
},
{
  "_id": {
    "$oid": "64ef55ed9134d0297553a684"
  },
  "name": "National School of Engineers of Gabes"
},
{
  "_id": {
    "$oid": "64ef55ed9134d0297553a685"
  },
  "name": "Higher Institute of Management of Gabes"
},
{
  "_id": {
    "$oid": "64ef55ed9134d0297553a686"
  },
  "name": "Higher Institute of Languages of Gabes"
},
{
  "_id": {
    "$oid": "64ef55ed9134d0297553a687"
  },
  "name": "Higher Institute of Arts and Crafts of Gabes"
},
{
  "_id": {
    "$oid": "64ef55ed9134d0297553a688"
  },
  "name": "Higher Institute of Applied Biology of Medenine"
},
{
  "_id": {
    "$oid": "64ef55ed9134d0297553a689"
  },
  "name": "Higher Institute of Legal Studies of Gabes"
},
{
  "_id": {
    "$oid": "64ef55ed9134d0297553a68a"
  },
  "name": "Higher Institute of Computing and Multimedia of Gabes"
},
{
  "_id": {
    "$oid": "64ef55ed9134d0297553a68b"
  },
  "name": "Higher Institute of Applied Sciences and Technology of Gabes"
},
{
  "_id": {
    "$oid": "64ef55ed9134d0297553a68c"
  },
  "name": "Higher Institute of Water Sciences and Techniques of Gabes"
},
{
  "_id": {
    "$oid": "64ef55ed9134d0297553a68d"
  },
  "name": "Higher Institute of Industrial Systems of Gabès"
},
{
  "_id": {
    "$oid": "64ef55ed9134d0297553a68e"
  },
  "name": "Higher Institute of Applied Studies in Humanities of Medenine"
},
{
  "_id": {
    "$oid": "64ef55ed9134d0297553a68f"
  },
  "name": "Higher Institute of Informatics of Medenine"
},
{
  "_id": {
    "$oid": "64ef55ed9134d0297553a690"
  },
  "name": "Higher Institute of Arts and Crafts of Tataouine"
},
{
  "_id": {
    "$oid": "64ef55ed9134d0297553a691"
  },
  "name": "Higher Institute of Nursing Sciences of Gabes"
},
{
  "_id": {
    "$oid": "64ef55ed9134d0297553a692"
  },
  "name": "PPE digital school"
},
{
  "_id": {
    "$oid": "64ef55ed9134d0297553a693"
  },
  "name": "Faculty of Paramedical and Health Sciences"
},
{
  "_id": {
    "$oid": "64ef55ed9134d0297553a694"
  },
  "name": "Faculty of Letters, Arts and Communication Sciences"
},
{
  "_id": {
    "$oid": "64ef55ed9134d0297553a695"
  },
  "name": "Faculty of Law and Management"
},
{
  "_id": {
    "$oid": "64ef55ed9134d0297553a696"
  },
  "name": "International Polytechnic School of Tunis"
},
{
  "_id": {
    "$oid": "64ef55ed9134d0297553a697"
  },
  "name": "Mediterranean School of Business"
},
{
  "_id": {
    "$oid": "64ef55ed9134d0297553a698"
  },
  "name": "Mediterranean Polytechnic School"
},
{
  "_id": {
    "$oid": "64ef55ed9134d0297553a699"
  },
  "name": "International School of Tunis"
},
{
  "_id": {
    "$oid": "64ef55ed9134d0297553a69a"
  },
  "name": "Central Polytechnic Higher School"
},
{
  "_id": {
    "$oid": "64ef55ed9134d0297553a69b"
  },
  "name": "Higher School of Engineering and Technology"
},
{
  "_id": {
    "$oid": "64ef55ed9134d0297553a69c"
  },
  "name": "Carthage Higher School of Science and Engineering"
},
{
  "_id": {
    "$oid": "64ef55ed9134d0297553a69d"
  },
  "name": "Carthage School of Management"
},
{
  "_id": {
    "$oid": "64ef55ed9134d0297553a69e"
  },
  "name": "Higher School of Law and Management"
},
{
  "_id": {
    "$oid": "64ef55ed9134d0297553a69f"
  },
  "name": "Higher School of Aeronautics and Technologies"
},
{
  "_id": {
    "$oid": "64ef55ed9134d0297553a6a0"
  },
  "name": "Higher School of Audiovisual and Design"
},
{
  "_id": {
    "$oid": "64ef55ed9134d0297553a6a1"
  },
  "name": "Higher School of Technology and Management"
},
{
  "_id": {
    "$oid": "64ef55ed9134d0297553a6a2"
  },
  "name": "Higher School of Information Technologies and Business Administration - Tunis"
},
{
  "_id": {
    "$oid": "64ef55ed9134d0297553a6a3"
  },
  "name": "Higher School of Technology and Engineering"
},
{
  "_id": {
    "$oid": "64ef55ed9134d0297553a6a4"
  },
  "name": "Higher School of Applied Sciences and Management"
},
{
  "_id": {
    "$oid": "64ef55ed9134d0297553a6a5"
  },
  "name": "Higher School of Business Administration and Law \"Avicenne\""
},
{
  "_id": {
    "$oid": "64ef55ed9134d0297553a6a6"
  },
  "name": "Higher School of Computer Science and Business Administration"
},
{
  "_id": {
    "$oid": "64ef55ed9134d0297553a6a7"
  },
  "name": "Higher School of Engineering and Communication"
},
{
  "_id": {
    "$oid": "64ef55ed9134d0297553a6a8"
  },
  "name": "Higher School of Engineering and Technological Studies of Tunis"
},
{
  "_id": {
    "$oid": "64ef55ed9134d0297553a6a9"
  },
  "name": "Higher Polytechnic School Ibn Khaldoun"
},
{
  "_id": {
    "$oid": "64ef55ed9134d0297553a6aa"
  },
  "name": "Law and Business School"
},
{
  "_id": {
    "$oid": "64ef55ed9134d0297553a6ab"
  },
  "name": "Maghreb Higher School of Science and Technology"
},
{
  "_id": {
    "$oid": "64ef55ed9134d0297553a6ac"
  },
  "name": "Mediterranean Faculty of Computer Science, Economics and Management of Tunis"
},
{
  "_id": {
    "$oid": "64ef55ed9134d0297553a6ad"
  },
  "name": "Faculty of Law, Economics and Management"
},
{
  "_id": {
    "$oid": "64ef55ed9134d0297553a6ae"
  },
  "name": "Faculty of Montplaisir"
},
{
  "_id": {
    "$oid": "64ef55ed9134d0297553a6af"
  },
  "name": "Faculty of Management Sciences and Technology in Mégrine"
},
{
  "_id": {
    "$oid": "64ef55ed9134d0297553a6b0"
  },
  "name": "Faculty of Health Sciences of Tunis"
},
{
  "_id": {
    "$oid": "64ef55ed9134d0297553a6b1"
  },
  "name": "Faculty of Legal, Social, Economic and Management Sciences"
},
{
  "_id": {
    "$oid": "64ef55ed9134d0297553a6b2"
  },
  "name": "Ibn Khaldoun Faculty of Law, Economics and Management"
},
{
  "_id": {
    "$oid": "64ef55ed9134d0297553a6b3"
  },
  "name": "International Higher Institute of Digital and Audiovisual Studies"
},
{
  "_id": {
    "$oid": "64ef55ed9134d0297553a6b4"
  },
  "name": "Institute of Higher Studies of Tunis"
},
{
  "_id": {
    "$oid": "64ef55ed9134d0297553a6b5"
  },
  "name": "Higher Institute of Paramedical Sciences \"Mahmoud Materi\""
},
{
  "_id": {
    "$oid": "64ef55ed9134d0297553a6b6"
  },
  "name": "Higher Institute of Business Administration"
},
{
  "_id": {
    "$oid": "64ef55ed9134d0297553a6b7"
  },
  "name": "Mediterranean Higher Institute of Technology"
},
{
  "_id": {
    "$oid": "64ef55ed9134d0297553a6b8"
  },
  "name": "Higher Polytechnic Institute"
},
{
  "_id": {
    "$oid": "64ef55ed9134d0297553a6b9"
  },
  "name": "Tunis Dauphine Higher Institute"
},
{
  "_id": {
    "$oid": "64ef55ed9134d0297553a6ba"
  },
  "name": "Private Polytechnic School of Sousse"
},
{
  "_id": {
    "$oid": "64ef55ed9134d0297553a6bb"
  },
  "name": "Private International School of Management of Sousse"
},
{
  "_id": {
    "$oid": "64ef55ed9134d0297553a6bc"
  },
  "name": "Private Higher School of Technology, Computer Science and Management of Sousse"
},
{
  "_id": {
    "$oid": "64ef55ed9134d0297553a6bd"
  },
  "name": "Private Higher School of Economics and Management of Sousse"
},
{
  "_id": {
    "$oid": "64ef55ed9134d0297553a6be"
  },
  "name": "Private Higher School of Engineering and Applied Technology"
},
{
  "_id": {
    "$oid": "64ef55ed9134d0297553a6bf"
  },
  "name": "Private Higher School of Engineering, Science and Technology of Sousse"
},
{
  "_id": {
    "$oid": "64ef55ed9134d0297553a6c0"
  },
  "name": "Private Higher School of Engineers of Sousse"
},
{
  "_id": {
    "$oid": "64ef55ed9134d0297553a6c1"
  },
  "name": "Private Faculty of Management and Administration Sciences of Sousse"
},
{
  "_id": {
    "$oid": "64ef55ed9134d0297553a6c2"
  },
  "name": "Private Institute of Advanced Studies of Sousse"
},
{
  "_id": {
    "$oid": "64ef55ed9134d0297553a6c3"
  },
  "name": "Private Higher Institute of Commercial Sciences and Business"
},
{
  "_id": {
    "$oid": "64ef55ed9134d0297553a6c4"
  },
  "name": "Private Higher Institute of Health Sciences of Sousse"
},
{
  "_id": {
    "$oid": "64ef55ed9134d0297553a6c5"
  },
  "name": "Private Higher Institute of Nursing Sciences \"EL AMED\""
},
{
  "_id": {
    "$oid": "64ef55ed9134d0297553a6c6"
  },
  "name": "Private Higher Institute of Nursing Sciences \"Etoile de formation\""
},
{
  "_id": {
    "$oid": "64ef55ed9134d0297553a6c7"
  },
  "name": "Private Higher Institute of Nursing Sciences of Sousse"
},
{
  "_id": {
    "$oid": "64ef55ed9134d0297553a6c8"
  },
  "name": "Private International School of Technology"
},
{
  "_id": {
    "$oid": "64ef55ed9134d0297553a6c9"
  },
  "name": "International Private Business School"
},
{
  "_id": {
    "$oid": "64ef55ed9134d0297553a6ca"
  },
  "name": "Private Higher School of Administrative and Commercial Studies of Sfax"
},
{
  "_id": {
    "$oid": "64ef55ed9134d0297553a6cb"
  },
  "name": "Private International Polytechnic School of Sfax"
},
{
  "_id": {
    "$oid": "64ef55ed9134d0297553a6cc"
  },
  "name": "Private Faculty of Paramedical Sciences of Sfax"
},
{
  "_id": {
    "$oid": "64ef55ed9134d0297553a6cd"
  },
  "name": "Private Higher Polytechnic Institute of Advanced Sciences of the South"
},
{
  "_id": {
    "$oid": "64ef55ed9134d0297553a6ce"
  },
  "name": "Private Faculty of Computer Science and Management of Nabeul"
},
{
  "_id": {
    "$oid": "64ef55ed9134d0297553a6cf"
  },
  "name": "Private Mediterranean School of Computer Science, Economics and Management of Nabeul"
},
{
  "_id": {
    "$oid": "64ef55ed9134d0297553a6d0"
  },
  "name": "Private Higher School of Information Technologies and Management of Nabeul"
},
{
  "_id": {
    "$oid": "64ef55ed9134d0297553a6d1"
  },
  "name": "Private Higher School of Engineers of Monastir"
},
{
  "_id": {
    "$oid": "64ef55ed9134d0297553a6d2"
  },
  "name": "Private Polytechnic School of Monastir"
},
{
  "_id": {
    "$oid": "64ef55ed9134d0297553a6d3"
  },
  "name": "Private Higher School of Applied Sciences and Technology of Gabès (private technological university of Gabès - Utech)"
},
{
  "_id": {
    "$oid": "64ef55ed9134d0297553a6d4"
  },
  "name": "Private Higher School of Engineers of Gafsa: ESIP Gafsa"
},
{
  "_id": {
    "$oid": "64ef55ed9134d0297553a6d5"
  },
  "name": "Private Higher Institute of Nursing Sciences of Kairouan: ISPSIK"
}]